[{"jref": "http://www.javlibrary.com/en/vl_searchbyid.php?keyword=SDMU-451", "_type": "dict", "code": "SDMU-451", "name": "\u7fbd\u6708\u5e0c", "pdat": ["\r\n\u7247\u540d\uff1a\u5e83\u702c\u3046\u307f\u306b\u3001\u6ce2\u591a\u91ce\u7d50\u8863\u3068\u7fbd\u6708\u5e0c\u304c\u6559\u3048\u308b\u30ec\u30ba\u306e\u4f5c\u6cd5", "\r\n\u5bb9\u91cf\uff1a4.05GB", "\r\n\u683c\u5f0f\uff1amp4", "\r\n\u914d\u4fe1\u958b\u59cb\u65e5\uff1a\u00a0 \u00a0 \u00a0 \u00a0 2017/01/06", "\r\n\u5546\u54c1\u767a\u58f2\u65e5\uff1a\u00a0 \u00a0 \u00a0 \u00a0 2017/01/06", "\r\n\u53ce\u9332\u6642\u9593\uff1a\u00a0 \u00a0 \u00a0 \u00a0 139\u5206 \uff08HD\u7248\uff1a139\u5206\uff09", "\r\n\u51fa\u6f14\u8005\uff1a\u00a0 \u00a0 \u00a0 \u00a0 \u5e83\u702c\u3046\u307f \u6ce2\u591a\u91ce\u7d50\u8863 \u7fbd\u6708\u5e0c", "\r\n\u76e3\u7763\uff1a\u00a0 \u00a0 \u00a0 \u00a0 \u68ee\u5ddd\u572d", "\r\n\u30b7\u30ea\u30fc\u30ba\uff1a\u00a0 \u00a0 \u00a0 \u00a0 ----", "\r\n\u30e1\u30fc\u30ab\u30fc\uff1a\u00a0 \u00a0 \u00a0 \u00a0 SOD\u30af\u30ea\u30a8\u30a4\u30c8", "\r\n\u30ec\u30fc\u30d9\u30eb\uff1a\u00a0 \u00a0 \u00a0 \u00a0 SOD\u30af\u30ea\u30a8\u30a4\u30c8", "\r\n\u30b8\u30e3\u30f3\u30eb\uff1a\u00a0 \u00a0 \u00a0 \u00a0 \u30cf\u30a4\u30d3\u30b8\u30e7\u30f3\u00a0\u00a0\u4f01\u756b\u00a0\u00a0\u30ec\u30ba\u00a0\u00a0\u30ec\u30ba\u30ad\u30b9\u00a0\u00a0\u30b9\u30ec\u30f3\u30c0\u30fc", "\r\n\u54c1\u756a\uff1a\u00a0 \u00a0 \u00a0 \u00a0 1sdmu00451", "\r\n\r\n"], "text": "[sdmu-451]\u5e83\u702c\u3046\u307f\u306b\u3001\u6ce2\u591a\u91ce\u7d50\u8863\u3068\u7fbd\u6708\u5e0c\u304c\u6559\u3048\u308b\u30ec\u30ba\u306e\u4f5c\u6cd5", "imgf": "https://www.goldenshark.xyz/images/SDMU-451.jpg", "href": "http://thz2.com/thread-966266-1-189.html", "dlnk": "http://thz2.com/forum.php?mod=attachment&aid=MzU1MjAxfGYzYjc1MmMzfDE1MjM5MjI1NTN8MHw5NjYyNjY%3D"}, {"jref": "http://www.javlibrary.com/en/vl_searchbyid.php?keyword=WANZ-575", "_type": "dict", "code": "WANZ-575", "name": "\u690e\u540d\u305d\u3089", "pdat": ["\r\n\u7247\u540d\uff1a\u3044\u3058\u3081\u3063\u5a18JK\u306e\u676d\u6253\u3061\u9a0e\u4e57\u4f4d\u4e2d\u51fa\u3057 \u690e\u540d\u305d\u3089", "\r\n\u5bb9\u91cf\uff1a3.41GB", "\r\n\u683c\u5f0f\uff1amp4", "\r\n\u914d\u4fe1\u958b\u59cb\u65e5\uff1a\u00a0 \u00a0 \u00a0 \u00a0 2017/01/01", "\r\n\u5546\u54c1\u767a\u58f2\u65e5\uff1a\u00a0 \u00a0 \u00a0 \u00a0 2017/01/07", "\r\n\u53ce\u9332\u6642\u9593\uff1a\u00a0 \u00a0 \u00a0 \u00a0 117\u5206 \uff08HD\u7248\uff1a117\u5206\uff09", "\r\n\u51fa\u6f14\u8005\uff1a\u00a0 \u00a0 \u00a0 \u00a0 \u690e\u540d\u305d\u3089", "\r\n\u76e3\u7763\uff1a\u00a0 \u00a0 \u00a0 \u00a0 ----", "\r\n\u30b7\u30ea\u30fc\u30ba\uff1a\u00a0 \u00a0 \u00a0 \u00a0 \u3044\u3058\u3081\u3063\u5a18JK\u306e\u676d\u6253\u3061\u9a0e\u4e57\u4f4d\u4e2d\u51fa\u3057", "\r\n\u30e1\u30fc\u30ab\u30fc\uff1a\u00a0 \u00a0 \u00a0 \u00a0 \u30ef\u30f3\u30ba\u30d5\u30a1\u30af\u30c8\u30ea\u30fc", "\r\n\u30ec\u30fc\u30d9\u30eb\uff1a\u00a0 \u00a0 \u00a0 \u00a0 WANZ", "\r\n\u30b8\u30e3\u30f3\u30eb\uff1a\u00a0 \u00a0 \u00a0 \u00a0 \u30cf\u30a4\u30d3\u30b8\u30e7\u30f3\u00a0\u00a0\u7368\u5360\u914d\u4fe1\u00a0\u00a0\u5358\u9ad4\u4f5c\u54c1\u00a0\u00a0\u9854\u9762\u9a0e\u4e57\u00a0\u00a0\u7661\u5973\u00a0\u00a0\u5973\u5b50\u6821\u751f\u00a0\u00a0\u4e2d\u51fa\u3057\u00a0\u00a0\u9a0e\u4e57\u4f4d", "\r\n\u54c1\u756a\uff1a\u00a0 \u00a0 \u00a0 \u00a0 wanz00575", "\r\n\r\n"], "text": "[wanz-575]\u3044\u3058\u3081\u3063\u5a18JK\u306e\u676d\u6253\u3061\u9a0e\u4e57\u4f4d\u4e2d\u51fa\u3057 \u690e\u540d\u305d\u3089", "imgf": "https://www.goldenshark.xyz/images/WANZ-575.jpg", "href": "http://thz2.com/thread-966271-1-189.html", "dlnk": "http://thz2.com/forum.php?mod=attachment&aid=MzU1MjA3fDI2MmE3YmY5fDE1MjM5MjI1NTR8MHw5NjYyNzE%3D"}, {"jref": "http://www.javlibrary.com/en/vl_searchbyid.php?keyword=GRCH-194", "_type": "dict", "code": "GRCH-194", "name": "\u4fdd\u5742\u3048\u308a", "pdat": ["\r\n\u7247\u540d\uff1a\u4e00\u5fb9\u304c\u8cb4\u5973\u306e\u30ef\u30ac\u30de\u30de\u306a\u6027\u6b32\u3001\u89e3\u653e\u3057\u307e\u3059\uff5e\u30aa\u30fc\u30c0\u30fcSEX\uff5e", "\r\n\u5bb9\u91cf\uff1a6.88GB", "\r\n\u683c\u5f0f\uff1amp4", "\r\n\u914d\u4fe1\u958b\u59cb\u65e5\uff1a\u00a0 \u00a0 \u00a0 \u00a0 2017/01/06", "\r\n\u5546\u54c1\u767a\u58f2\u65e5\uff1a\u00a0 \u00a0 \u00a0 \u00a0 2017/01/06", "\r\n\u53ce\u9332\u6642\u9593\uff1a\u00a0 \u00a0 \u00a0 \u00a0 235\u5206 \uff08HD\u7248\uff1a235\u5206\uff09", "\r\n\u51fa\u6f14\u8005\uff1a\u00a0 \u00a0 \u00a0 \u00a0 \u6ce2\u591a\u91ce\u7d50\u8863 \u4fdd\u5742\u3048\u308a \u4eca\u5bae\u3044\u305a\u307f / \u4e00\u5fb9\uff08\u9234\u6728\u4e00\u5fb9\uff09", "\r\n\u76e3\u7763\uff1a\u00a0 \u00a0 \u00a0 \u00a0 \u897f\u4e2d\u5cf6\u5357\u65b9", "\r\n\u30b7\u30ea\u30fc\u30ba\uff1a\u00a0 \u00a0 \u00a0 \u00a0 ----", "\r\n\u30e1\u30fc\u30ab\u30fc\uff1a\u00a0 \u00a0 \u00a0 \u00a0 SOD\u30af\u30ea\u30a8\u30a4\u30c8", "\r\n\u30ec\u30fc\u30d9\u30eb\uff1a\u00a0 \u00a0 \u00a0 \u00a0 GIRL\u2019S CH", "\r\n\u30b8\u30e3\u30f3\u30eb\uff1a\u00a0 \u00a0 \u00a0 \u00a0 \u30cf\u30a4\u30d3\u30b8\u30e7\u30f3\u00a0\u00a0\u4f01\u756b\u00a0\u00a0\u5973\u6027\u5411\u3051\u00a0\u00a0\u96fb\u30de\u00a0\u00a0\u62d8\u675f\u00a0\u00a0\u8abf\u6559?\u5974\u96b7\u00a0\u00a0\u6f6e\u5439\u304d\u00a0\u00a0\u30ad\u30b9?\u63a5\u543b", "\r\n\u54c1\u756a\uff1a\u00a0 \u00a0 \u00a0 \u00a0 1grch00194", "\r\n\r\n"], "text": "[grch-194]\u4e00\u5fb9\u304c\u8cb4\u5973\u306e\u30ef\u30ac\u30de\u30de\u306a\u6027\u6b32", "imgf": "https://www.goldenshark.xyz/images/GRCH-194.jpg", "href": "http://thz2.com/thread-966218-1-189.html", "dlnk": "http://thz2.com/forum.php?mod=attachment&aid=MzU1MTY1fDFjZWNkZDdifDE1MjM5MjI1NTR8MHw5NjYyMTg%3D"}, {"jref": "http://www.javlibrary.com/en/vl_searchbyid.php?keyword=MIAE-006", "_type": "dict", "code": "MIAE-006", "name": "\u690e\u540d\u305d\u3089", "pdat": ["\r\n\u7247\u540d\uff1a\u79c1\u304c\u4f55\u5ea6\u3082\u30a4\u30af\u307e\u3067\u7d76\u5bfe\u306b\u5c04\u7cbe\u3055\u305b\u306a\u3044\u8d85\u7d76\u7126\u3089\u3057JK \u690e\u540d\u305d\u3089", "\r\n\u5bb9\u91cf\uff1a3.42GB", "\r\n\u683c\u5f0f\uff1amp4", "\r\n\u914d\u4fe1\u958b\u59cb\u65e5\uff1a\u00a0 \u00a0 \u00a0 \u00a0 2017/01/01", "\r\n\u5546\u54c1\u767a\u58f2\u65e5\uff1a\u00a0 \u00a0 \u00a0 \u00a0 2017/01/07", "\r\n\u53ce\u9332\u6642\u9593\uff1a\u00a0 \u00a0 \u00a0 \u00a0 117\u5206 \uff08HD\u7248\uff1a117\u5206\uff09", "\r\n\u51fa\u6f14\u8005\uff1a\u00a0 \u00a0 \u00a0 \u00a0 \u690e\u540d\u305d\u3089", "\r\n\u76e3\u7763\uff1a\u00a0 \u00a0 \u00a0 \u00a0 \u30c9\u30e9\u30b4\u30f3\u897f\u5ddd", "\r\n\u30b7\u30ea\u30fc\u30ba\uff1a\u00a0 \u00a0 \u00a0 \u00a0 ----", "\r\n\u30e1\u30fc\u30ab\u30fc\uff1a\u00a0 \u00a0 \u00a0 \u00a0 \u30e0\u30fc\u30c7\u30a3\u30fc\u30ba", "\r\n\u30ec\u30fc\u30d9\u30eb\uff1a\u00a0 \u00a0 \u00a0 \u00a0 MOODYZ ACID", "\r\n\u30b8\u30e3\u30f3\u30eb\uff1a\u00a0 \u00a0 \u00a0 \u00a0 \u9a0e\u4e57\u4f4d\u00a0\u00a0\u5973\u5b50\u6821\u751f\u00a0\u00a03P?4P\u00a0\u00a0\u30b7\u30c3\u30af\u30b9\u30ca\u30a4\u30f3\u00a0\u00a0\u5358\u9ad4\u4f5c\u54c1\u00a0\u00a0\u30c7\u30b8\u30e2\u00a0\u00a0\u7368\u5360\u914d\u4fe1\u00a0\u00a0\u30cf\u30a4\u30d3\u30b8\u30e7\u30f3\u00a0\u00a0\u9854\u9762\u9a0e\u4e57", "\r\n\u54c1\u756a\uff1a\u00a0 \u00a0 \u00a0 \u00a0 miae00006", "\r\n\r\n"], "text": "[miae-006]\u7d76\u5bfe\u306b\u5c04\u7cbe\u3055\u305b\u306a\u3044\u8d85\u7d76\u7126\u3089\u3057JK \u690e\u540d\u305d\u3089", "imgf": "https://www.goldenshark.xyz/images/MIAE-006.jpg", "href": "http://thz2.com/thread-964673-1-189.html", "dlnk": "http://thz2.com/forum.php?mod=attachment&aid=MzU1MDA0fDRkYTEzMDU0fDE1MjM5MjI1NTV8MHw5NjQ2NzM%3D"}, {"jref": "http://www.javlibrary.com/en/vl_searchbyid.php?keyword=MIGD-758", "_type": "dict", "code": "MIGD-758", "name": "\u304d\u307f\u3068\u6b69\u7f8e", "pdat": ["\r\n\u7247\u540d\uff1a\u5b8c\u5168\u30ce\u30fc\u30ab\u30c3\u30c8\u771f\u6027\u4e2d\u51fa\u3057 \u304d\u307f\u3068\u6b69\u5b9f", "\r\n\u5bb9\u91cf\uff1a4.09GB", "\r\n\u683c\u5f0f\uff1amp4", "\r\n\u914d\u4fe1\u958b\u59cb\u65e5\uff1a\u00a0 \u00a0 \u00a0 \u00a0 2017/01/01", "\r\n\u5546\u54c1\u767a\u58f2\u65e5\uff1a\u00a0 \u00a0 \u00a0 \u00a0 2017/01/07", "\r\n\u53ce\u9332\u6642\u9593\uff1a\u00a0 \u00a0 \u00a0 \u00a0 140\u5206 \uff08HD\u7248\uff1a140\u5206\uff09", "\r\n\u51fa\u6f14\u8005\uff1a\u00a0 \u00a0 \u00a0 \u00a0 \u304d\u307f\u3068\u6b69\u5b9f", "\r\n\u76e3\u7763\uff1a\u00a0 \u00a0 \u00a0 \u00a0 \u5357\u2605\u6ce2\u738b", "\r\n\u30b7\u30ea\u30fc\u30ba\uff1a\u00a0 \u00a0 \u00a0 \u00a0 \u771f\u6027\u4e2d\u51fa\u3057", "\r\n\u30e1\u30fc\u30ab\u30fc\uff1a\u00a0 \u00a0 \u00a0 \u00a0 \u30e0\u30fc\u30c7\u30a3\u30fc\u30ba", "\r\n\u30ec\u30fc\u30d9\u30eb\uff1a\u00a0 \u00a0 \u00a0 \u00a0 MOODYZ Gati", "\r\n\u30b8\u30e3\u30f3\u30eb\uff1a\u00a0 \u00a0 \u00a0 \u00a0 \u30cf\u30a4\u30d3\u30b8\u30e7\u30f3\u00a0\u00a0\u7368\u5360\u914d\u4fe1\u00a0\u00a0\u30c7\u30b8\u30e2\u00a0\u00a0\u6c57\u3060\u304f\u00a0\u00a0\u5358\u9ad4\u4f5c\u54c1\u00a0\u00a0\u7f8e\u5c11\u5973\u00a0\u00a0\u4e2d\u51fa\u3057", "\r\n\u54c1\u756a\uff1a\u00a0 \u00a0 \u00a0 \u00a0 migd00758", "\r\n\r\n"], "text": "[migd-758]\u5b8c\u5168\u30ce\u30fc\u30ab\u30c3\u30c8\u771f\u6027\u4e2d\u51fa\u3057 \u304d\u307f\u3068\u6b69\u5b9f", "imgf": "https://www.goldenshark.xyz/images/MIGD-758.jpg", "href": "http://thz2.com/thread-964667-1-189.html", "dlnk": "http://thz2.com/forum.php?mod=attachment&aid=MzU0OTk0fDAxNGIwNzdifDE1MjM5MjI1NTZ8MHw5NjQ2Njc%3D"}, {"jref": "http://www.javlibrary.com/en/vl_searchbyid.php?keyword=MIAE-002", "_type": "dict", "code": "MIAE-002", "name": "\u4eca\u5bae\u3044\u305a\u307f", "pdat": ["\r\n\u7247\u540d\uff1a\u5730\u5143\u306eDQN\u9054\u306b\u5f7c\u5973\u3092\u596a\u308f\u308c\u3066\u4f55\u3082\u51fa\u6765\u306a\u3044\u50d5\u3002 \u4eca\u5bae\u3044\u305a\u307f", "\r\n\u5bb9\u91cf\uff1a3.73GB", "\r\n\u683c\u5f0f\uff1amp4", "\r\n\u914d\u4fe1\u958b\u59cb\u65e5\uff1a\u00a0 \u00a0 \u00a0 \u00a0 2017/01/01", "\r\n\u5546\u54c1\u767a\u58f2\u65e5\uff1a\u00a0 \u00a0 \u00a0 \u00a0 2017/01/07", "\r\n\u53ce\u9332\u6642\u9593\uff1a\u00a0 \u00a0 \u00a0 \u00a0 130\u5206 \uff08HD\u7248\uff1a130\u5206\uff09", "\r\n\u51fa\u6f14\u8005\uff1a\u00a0 \u00a0 \u00a0 \u00a0 \u4eca\u5bae\u3044\u305a\u307f", "\r\n\u76e3\u7763\uff1a\u00a0 \u00a0 \u00a0 \u00a0 X", "\r\n\u30b7\u30ea\u30fc\u30ba\uff1a\u00a0 \u00a0 \u00a0 \u00a0 \u5730\u5143\u306eDQN\u9054\u306b\u5f7c\u5973\u3092\u596a\u308f\u308c\u3066\u4f55\u3082\u51fa\u4f86\u306a\u3044\u50d5\u3002", "\r\n\u30e1\u30fc\u30ab\u30fc\uff1a\u00a0 \u00a0 \u00a0 \u00a0 \u30e0\u30fc\u30c7\u30a3\u30fc\u30ba", "\r\n\u30ec\u30fc\u30d9\u30eb\uff1a\u00a0 \u00a0 \u00a0 \u00a0 MOODYZ ACID", "\r\n\u30b8\u30e3\u30f3\u30eb\uff1a\u00a0 \u00a0 \u00a0 \u00a0 \u30c9\u30e9\u30de\u00a0\u00a0\u5de8\u4e73\u00a0\u00a0\u8f2a\u59e6\u00a0\u00a0\u30a4\u30e9\u30de\u30c1\u30aa\u00a0\u00a0\u5358\u9ad4\u4f5c\u54c1\u00a0\u00a0\u30c7\u30b8\u30e2\u00a0\u00a0\u7368\u5360\u914d\u4fe1\u00a0\u00a0\u30cf\u30a4\u30d3\u30b8\u30e7\u30f3\u00a0\u00a0\u5be2\u53d6\u308a?\u5be2\u53d6\u3089\u308c", "\r\n\u54c1\u756a\uff1a\u00a0 \u00a0 \u00a0 \u00a0 miae00002", "\r\n\r\n"], "text": "[miae-002]\u5f7c\u5973\u3092\u596a\u308f\u308c\u3066\u4f55\u3082\u51fa\u6765\u306a\u3044\u50d5\u3002 \u4eca\u5bae\u3044\u305a\u307f", "imgf": "https://www.goldenshark.xyz/images/MIAE-002.jpg", "href": "http://thz2.com/thread-964668-1-189.html", "dlnk": "http://thz2.com/forum.php?mod=attachment&aid=MzU0OTk2fDQ1ZDEzNzRlfDE1MjM5MjI1NTZ8MHw5NjQ2Njg%3D"}, {"jref": "http://www.javlibrary.com/en/vl_searchbyid.php?keyword=MIAE-005", "_type": "dict", "code": "MIAE-005", "name": "\u6804\u5ddd\u4e43\u4e9c", "pdat": ["\r\n\u7247\u540d\uff1a\u65e9\u6f0f\u30a4\u30af\u30a4\u30af\u5973\u5b50\u6821\u751f6 \u6804\u5ddd\u4e43\u4e9c", "\r\n\u5bb9\u91cf\uff1a3.45GB", "\r\n\u683c\u5f0f\uff1amp4", "\r\n\u914d\u4fe1\u958b\u59cb\u65e5\uff1a\u00a0 \u00a0 \u00a0 \u00a0 2017/01/01", "\r\n\u5546\u54c1\u767a\u58f2\u65e5\uff1a\u00a0 \u00a0 \u00a0 \u00a0 2017/01/07", "\r\n\u53ce\u9332\u6642\u9593\uff1a\u00a0 \u00a0 \u00a0 \u00a0 119\u5206 \uff08HD\u7248\uff1a119\u5206\uff09", "\r\n\u51fa\u6f14\u8005\uff1a\u00a0 \u00a0 \u00a0 \u00a0 \u6804\u5ddd\u4e43\u4e9c", "\r\n\u76e3\u7763\uff1a\u00a0 \u00a0 \u00a0 \u00a0 \u91d1\u7530\u4e00\u5c0f\u4e94\u90ce", "\r\n\u30b7\u30ea\u30fc\u30ba\uff1a\u00a0 \u00a0 \u00a0 \u00a0 \u65e9\u6f0f\u30a4\u30af\u30a4\u30af\u5973\u5b50\u6821\u751f", "\r\n\u30e1\u30fc\u30ab\u30fc\uff1a\u00a0 \u00a0 \u00a0 \u00a0 \u30e0\u30fc\u30c7\u30a3\u30fc\u30ba", "\r\n\u30ec\u30fc\u30d9\u30eb\uff1a\u00a0 \u00a0 \u00a0 \u00a0 MOODYZ ACID", "\r\n\u30b8\u30e3\u30f3\u30eb\uff1a\u00a0 \u00a0 \u00a0 \u00a0 \u30cf\u30a4\u30d3\u30b8\u30e7\u30f3\u00a0\u00a0\u7368\u5360\u914d\u4fe1\u00a0\u00a0\u30c7\u30b8\u30e2\u00a0\u00a0\u5358\u9ad4\u4f5c\u54c1\u00a0\u00a0\u6f6e\u5439\u304d\u00a0\u00a0\u7f8e\u5c11\u5973\u00a0\u00a0\u8abf\u6559?\u5974\u96b7\u00a0\u00a0\u5973\u5b50\u6821\u751f", "\r\n\u54c1\u756a\uff1a\u00a0 \u00a0 \u00a0 \u00a0 miae00005", "\r\n\r\n"], "text": "[miae-005]\u65e9\u6f0f\u30a4\u30af\u30a4\u30af\u5973\u5b50\u6821\u751f6 \u6804\u5ddd\u4e43\u4e9c", "imgf": "https://www.goldenshark.xyz/images/MIAE-005.jpg", "href": "http://thz2.com/thread-964672-1-189.html", "dlnk": "http://thz2.com/forum.php?mod=attachment&aid=MzU1MDAyfDBjYzkxMjM1fDE1MjM5MjI1NTd8MHw5NjQ2NzI%3D"}, {"jref": "http://www.javlibrary.com/en/vl_searchbyid.php?keyword=CJOD-060", "_type": "dict", "code": "CJOD-060", "name": "\u6804\u5ddd\u4e43\u4e9c", "pdat": ["\r\n\u7247\u540d\uff1a\u8a98\u60d1\u4e2d\u51fa\u3057\u56de\u6625\u30a8\u30b9\u30c6\u30b5\u30ed\u30f3 \u6804\u5ddd\u4e43\u4e9c", "\r\n\u5bb9\u91cf\uff1a3.45GB", "\r\n\u683c\u5f0f\uff1amp4", "\r\n\u914d\u4fe1\u958b\u59cb\u65e5\uff1a\u00a0 \u00a0 \u00a0 \u00a0 2016/12/29", "\r\n\u5546\u54c1\u767a\u58f2\u65e5\uff1a\u00a0 \u00a0 \u00a0 \u00a0 2017/01/01", "\r\n\u53ce\u9332\u6642\u9593\uff1a\u00a0 \u00a0 \u00a0 \u00a0 119\u5206 \uff08HD\u7248\uff1a119\u5206\uff09", "\r\n\u51fa\u6f14\u8005\uff1a\u00a0 \u00a0 \u00a0 \u00a0 \u6804\u5ddd\u4e43\u4e9c", "\r\n\u76e3\u7763\uff1a\u00a0 \u00a0 \u00a0 \u00a0 \u4e2d\u76ee\u9ed2\u6d69\u6cbb", "\r\n\u30b7\u30ea\u30fc\u30ba\uff1a\u00a0 \u00a0 \u00a0 \u00a0 \u8a98\u60d1\u4e2d\u51fa\u3057\u56de\u6625\u30a8\u30b9\u30c6\u30b5\u30ed\u30f3", "\r\n\u30e1\u30fc\u30ab\u30fc\uff1a\u00a0 \u00a0 \u00a0 \u00a0 \u7661\u5973\u30d8\u30d6\u30f3\uff08\u7f8e\uff09", "\r\n\u30ec\u30fc\u30d9\u30eb\uff1a\u00a0 \u00a0 \u00a0 \u00a0 \u7661\u5973\u30d8\u30d6\u30f3", "\r\n\u30b8\u30e3\u30f3\u30eb\uff1a\u00a0 \u00a0 \u00a0 \u00a0 \u30cf\u30a4\u30d3\u30b8\u30e7\u30f3\u00a0\u00a0\u7368\u5360\u914d\u4fe1\u00a0\u00a0\u5358\u9ad4\u4f5c\u54c1\u00a0\u00a0\u6deb\u8a9e\u00a0\u00a0\u9a0e\u4e57\u4f4d\u00a0\u00a0\u7f8e\u5c11\u5973\u00a0\u00a0\u7661\u5973\u00a0\u00a0\u30a8\u30b9\u30c6", "\r\n\u54c1\u756a\uff1a\u00a0 \u00a0 \u00a0 \u00a0 cjod00060", "\r\n\r\n"], "text": "[cjod-060]\u8a98\u60d1\u4e2d\u51fa\u3057\u56de\u6625\u30a8\u30b9\u30c6\u30b5\u30ed\u30f3 \u6804\u5ddd\u4e43\u4e9c", "imgf": "https://www.goldenshark.xyz/images/CJOD-060.jpg", "href": "http://thz2.com/thread-964660-1-190.html", "dlnk": "http://thz2.com/forum.php?mod=attachment&aid=MzU0OTg0fDM3MmIyYTM4fDE1MjM5MjI1NTd8MHw5NjQ2NjA%3D"}, {"jref": "http://www.javlibrary.com/en/vl_searchbyid.php?keyword=ABP-551", "_type": "dict", "code": "ABP-551", "name": "\u5712\u7530\u307f\u304a\u3093", "pdat": ["\r\n\u7247\u540d\uff1a\u5712\u7530\u307f\u304a\u3093 \u306a\u307e\u306a\u304b\u3060\u3057 14", "\r\n\u5bb9\u91cf\uff1a3.90GB", "\r\n\u683c\u5f0f\uff1amp4", "\r\n\u914d\u4fe1\u958b\u59cb\u65e5\uff1a\u00a0 \u00a0 \u00a0 \u00a0 2017/01/06", "\r\n\u5546\u54c1\u767a\u58f2\u65e5\uff1a\u00a0 \u00a0 \u00a0 \u00a0 2017/01/06", "\r\n\u53ce\u9332\u6642\u9593\uff1a\u00a0 \u00a0 \u00a0 \u00a0 135\u5206 \uff08HD\u7248\uff1a135\u5206\uff09", "\r\n\u51fa\u6f14\u8005\uff1a\u00a0 \u00a0 \u00a0 \u00a0 \u5712\u7530\u307f\u304a\u3093", "\r\n\u76e3\u7763\uff1a\u00a0 \u00a0 \u00a0 \u00a0 \u307f\u3061\u308b\u30b5\u30f3", "\r\n\u30b7\u30ea\u30fc\u30ba\uff1a\u00a0 \u00a0 \u00a0 \u00a0 \u306a\u307e\u306a\u304b\u3060\u3057", "\r\n\u30e1\u30fc\u30ab\u30fc\uff1a\u00a0 \u00a0 \u00a0 \u00a0 \u30d7\u30ec\u30b9\u30c6\u30fc\u30b8", "\r\n\u30ec\u30fc\u30d9\u30eb\uff1a\u00a0 \u00a0 \u00a0 \u00a0 ABSOLUTELY PERFECT", "\r\n\u30b8\u30e3\u30f3\u30eb\uff1a\u00a0 \u00a0 \u00a0 \u00a0 \u5358\u9ad4\u4f5c\u54c1\u00a0\u00a0\u9854\u5c04\u00a0\u00a03P?4P\u00a0\u00a0\u30d1\u30a4\u30ba\u30ea\u00a0\u00a0\u4e2d\u51fa\u3057\u00a0\u00a0\u5de8\u4e73\u00a0\u00a0\u30cf\u30a4\u30d3\u30b8\u30e7\u30f3", "\r\n\u54c1\u756a\uff1a\u00a0 \u00a0 \u00a0 \u00a0 118abp00551", "\r\n\r\n"], "text": "[abp-551]\u5712\u7530\u307f\u304a\u3093 \u306a\u307e\u306a\u304b\u3060\u3057 14", "imgf": "https://www.goldenshark.xyz/images/ABP-551.jpg", "href": "http://thz2.com/thread-964654-1-190.html", "dlnk": "http://thz2.com/forum.php?mod=attachment&aid=MzU0OTcyfGYxM2UzNWI1fDE1MjM5MjI1NTh8MHw5NjQ2NTQ%3D"}, {"jref": "http://www.javlibrary.com/en/vl_searchbyid.php?keyword=HUNTA-245", "_type": "dict", "code": "HUNTA-245", "name": "\u767d\u6843\u5fc3\u5948", "pdat": ["\r\n\u7247\u540d\uff1a\u90fd\u4f1a\u306b\u61a7\u308c\u308b\u7530\u820e\u8005\u5973\u5b50\u3068\u5b9f\u5bb6\u306e\u3053\u305f\u3064\u3067\u7537\u306f\u30dc\u30af\u3072\u3068\u308a\u306e\u738b\u69d8\u30b2\u30fc\u30e0\uff01\uff01\u7530\u820e\u8005\u306e\u30dc\u30af\u306f\u90fd\u4f1a\u306b\u51fa\u3066\u4e00\u4eba\u66ae\u3089\u3057\u3092\u59cb\u3081\u3001\u5c02\u9580\u5b66\u6821\u306b\u901a\u3063\u3066\u3044\u308b\u3093\u3067\u3059\u304c\u2026\u4f55\u3082\u30a4\u30a4\u4e8b\u306a\u304f\u4e00\u5e74\u304c\u7d42\u308f\u308a\u307e\u3057\u305f\u3002\u305d\u3093\u306a\u30dc\u30af\u304c\u6b63\u6708\u5b9f\u5bb6\u306b\u5e30\u308b\u3068\u3001\u5f85\u3063\u3066\u3044\u305f\u306e\u306f\u5730\u5143\u306b\u4f4f\u3080\u89aa\u621a\u305f\u3061\uff01\u3057\u304b\u3082\u5973\u5b50\u3070\u304b\u2026", "\r\n\u5bb9\u91cf\uff1a7.04GB", "\r\n\u683c\u5f0f\uff1amp4", "\r\n\u914d\u4fe1\u958b\u59cb\u65e5\uff1a\u00a0 \u00a0 \u00a0 \u00a0 2017/01/02", "\r\n\u5546\u54c1\u767a\u58f2\u65e5\uff1a\u00a0 \u00a0 \u00a0 \u00a0 2017/01/07", "\r\n\u53ce\u9332\u6642\u9593\uff1a\u00a0 \u00a0 \u00a0 \u00a0 241\u5206 \uff08HD\u7248\uff1a241\u5206\uff09", "\r\n\u51fa\u6f14\u8005\uff1a\u00a0 \u00a0 \u00a0 \u00a0 ----", "\r\n\u76e3\u7763\uff1a\u00a0 \u00a0 \u00a0 \u00a0 \u30b3\u30f3\u30cb\u30e3\u30c3\u30af\u795e\u91ce", "\r\n\u30b7\u30ea\u30fc\u30ba\uff1a\u00a0 \u00a0 \u00a0 \u00a0 \u738b\u69d8\u30b2\u30fc\u30e0", "\r\n\u30e1\u30fc\u30ab\u30fc\uff1a\u00a0 \u00a0 \u00a0 \u00a0 Hunter", "\r\n\u30ec\u30fc\u30d9\u30eb\uff1a\u00a0 \u00a0 \u00a0 \u00a0 Hunter\uff08HHH\u30b0\u30eb\u30fc\u30d7\uff09", "\r\n\u30b8\u30e3\u30f3\u30eb\uff1a\u00a0 \u00a0 \u00a0 \u00a0 \u7368\u5360\u914d\u4fe1\u00a0\u00a0\u9a0e\u4e57\u4f4d\u00a0\u00a0\u5de8\u4e73\u00a0\u00a04\u6642\u9593\u4ee5\u4e0a\u4f5c\u54c1\u00a0\u00a03P?4P\u00a0\u00a0\u30cf\u30fc\u30ec\u30e0\u00a0\u00a0\u30cf\u30a4\u30d3\u30b8\u30e7\u30f3", "\r\n\u54c1\u756a\uff1a\u00a0 \u00a0 \u00a0 \u00a0 hunta00245", "\r\n\r\n"], "text": "[hunta-245]\u90fd\u4f1a\u306b\u61a7\u308c\u308b\u7530\u820e\u8005\u5973\u5b50\u3068\u5b9f\u5bb6", "imgf": "https://www.goldenshark.xyz/images/HUNTA-245.jpg", "href": "http://thz2.com/thread-964647-1-190.html", "dlnk": "http://thz2.com/forum.php?mod=attachment&aid=MzU0OTU4fGFkNjFhZDI5fDE1MjM5MjI1NTh8MHw5NjQ2NDc%3D"}, {"jref": "http://www.javlibrary.com/en/vl_searchbyid.php?keyword=HUNTA-248", "_type": "dict", "code": "HUNTA-248", "name": "\u5c3e\u4e0a\u82e5\u8449", "pdat": ["\r\n\u7247\u540d\uff1a\u300c\u4f55\u3067\u52d5\u304b\u3059\u306e\uff01\u30c0\u30e1\u3067\u3057\u3087\u3046\uff01\u30c0\u30e1\u30c0\u30e1\u672c\u5f53\u306b\u633f\u3063\u3061\u3083\u3046\u304b\u3089\u30c0\u30e1\uff01\uff01\u300d\u30cc\u30eb\u3063\u3068\u751f\u633f\u5165\u3067\u7d50\u5c40\u629c\u304b\u305a\u306e4\u9023\u7d9a\u4e2d\u51fa\u3057\uff01\uff01\u8d85\u5de8\u4e73\u904e\u304e\u308b\u30dc\u30af\u306e\u5bb6\u5ead\u6559\u5e2b\u306f\u80f8\u306e\u8c37\u9593\u304c\u5e38\u306b\u898b\u3048\u3066\u3044\u307e\u3059\uff01\uff01\u53d7\u9a13\u751f\u306e\u30dc\u30af\u306b\u306f\u76ee\u306e\u731b\u6bd2\u3067\u3059\uff01\u6bce\u5ea6\u6bce\u5ea6\u80f8\u306e\u8c37\u9593\u3067\u52c3\u8d77\u3057\u3066\u52c9\u5f37\u304c\u624b\u306b\u4ed8\u304d\u307e\u305b\u3093\uff01\uff01\u3055\u2026", "\r\n\u5bb9\u91cf\uff1a10.3GB", "\r\n\u683c\u5f0f\uff1amp4", "\r\n\u914d\u4fe1\u958b\u59cb\u65e5\uff1a\u00a0 \u00a0 \u00a0 \u00a0 2017/01/02", "\r\n\u5546\u54c1\u767a\u58f2\u65e5\uff1a\u00a0 \u00a0 \u00a0 \u00a0 2017/01/07", "\r\n\u53ce\u9332\u6642\u9593\uff1a\u00a0 \u00a0 \u00a0 \u00a0 353\u5206 \uff08HD\u7248\uff1a353\u5206\uff09", "\r\n\u51fa\u6f14\u8005\uff1a\u00a0 \u00a0 \u00a0 \u00a0 ----", "\r\n\u76e3\u7763\uff1a\u00a0 \u00a0 \u00a0 \u00a0 \u30dc\u30eb\u30dc\u4e2d\u91ce", "\r\n\u30b7\u30ea\u30fc\u30ba\uff1a\u00a0 \u00a0 \u00a0 \u00a0 \u30dc\u30af\u306e\u5bb6\u5ead\u6559\u5e2b\uff08Hunter\uff09", "\r\n\u30e1\u30fc\u30ab\u30fc\uff1a\u00a0 \u00a0 \u00a0 \u00a0 Hunter", "\r\n\u30ec\u30fc\u30d9\u30eb\uff1a\u00a0 \u00a0 \u00a0 \u00a0 Hunter\uff08HHH\u30b0\u30eb\u30fc\u30d7\uff09", "\r\n\u30b8\u30e3\u30f3\u30eb\uff1a\u00a0 \u00a0 \u00a0 \u00a0 \u7368\u5360\u914d\u4fe1\u00a0\u00a0\u4e2d\u51fa\u3057\u00a0\u00a0\u9a0e\u4e57\u4f4d\u00a0\u00a0\u30cf\u30a4\u30d3\u30b8\u30e7\u30f3\u00a0\u00a04\u6642\u9593\u4ee5\u4e0a\u4f5c\u54c1\u00a0\u00a0\u5de8\u4e73\u00a0\u00a0\u5bb6\u5ead\u6559\u5e2b", "\r\n\u54c1\u756a\uff1a\u00a0 \u00a0 \u00a0 \u00a0 hunta00248", "\r\n\r\n"], "text": "[hunta-248]\u8d85\u5de8\u4e73\u904e\u304e\u308b\u30dc\u30af\u306e\u5bb6\u5ead\u6559\u5e2b", "imgf": "https://www.goldenshark.xyz/images/HUNTA-248.jpg", "href": "http://thz2.com/thread-964650-1-190.html", "dlnk": "http://thz2.com/forum.php?mod=attachment&aid=MzU0OTY0fDlmMGYyZTJhfDE1MjM5MjI1NTl8MHw5NjQ2NTA%3D"}, {"jref": "http://www.javlibrary.com/en/vl_searchbyid.php?keyword=JKSR-259", "_type": "dict", "code": "JKSR-259", "name": "\u6589\u85e4\u307f\u3086", "pdat": ["\r\n\u7247\u540d\uff1a\u7530\u820e\u5a18\u3001\u6642\u7d66696\u5186\u3002\u3010\u8d85\u3011\u5e78\u305b\u611b\u4eba\u5951\u7d04 \u307f\u3086 \u81ea\u5206\u306e\u4fa1\u5024\u3092\u3088\u304f\u89e3\u3063\u3066\u3044\u306a\u3044\u5730\u5473\u30ab\u30ef\u7d20\u6734\u30ac\u30fc\u30eb\u304c\u6700\u4f4e\u8cc3\u91d1\u3067\u30e4\u30e9\u308c\u307e\u304f\u308a\u306e\u4e2d\u51fa\u3057\u3002", "\r\n\u5bb9\u91cf\uff1a3.60GB", "\r\n\u683c\u5f0f\uff1amp4", "\r\n\u914d\u4fe1\u958b\u59cb\u65e5\uff1a\u00a0 \u00a0 \u00a0 \u00a0 2016/12/25", "\r\n\u5546\u54c1\u767a\u58f2\u65e5\uff1a\u00a0 \u00a0 \u00a0 \u00a0 2016/12/25", "\r\n\u53ce\u9332\u6642\u9593\uff1a\u00a0 \u00a0 \u00a0 \u00a0 123\u5206 \uff08HD\u7248\uff1a123\u5206\uff09", "\r\n\u51fa\u6f14\u8005\uff1a\u00a0 \u00a0 \u00a0 \u00a0 ----", "\r\n\u76e3\u7763\uff1a\u00a0 \u00a0 \u00a0 \u00a0 obockey", "\r\n\u30b7\u30ea\u30fc\u30ba\uff1a\u00a0 \u00a0 \u00a0 \u00a0 \u7530\u820e\u5a18\u3001\u6642\u7d66\u25cb\u25cb\u5186\u3002", "\r\n\u30e1\u30fc\u30ab\u30fc\uff1a\u00a0 \u00a0 \u00a0 \u00a0 \u30d3\u30c3\u30b0\u30e2\u30fc\u30ab\u30eb", "\r\n\u30ec\u30fc\u30d9\u30eb\uff1a\u00a0 \u00a0 \u00a0 \u00a0 \u30d4\u30f3\u30af\u30b8\u30e3\u30f3\u30ad\u30fc", "\r\n\u30b8\u30e3\u30f3\u30eb\uff1a\u00a0 \u00a0 \u00a0 \u00a0 \u30cf\u30a4\u30d3\u30b8\u30e7\u30f3\u00a0\u00a0\u4e2d\u51fa\u3057\u00a0\u00a0\u30df\u30cb\u7cfb\u00a0\u00a0\u30c9\u30ad\u30e5\u30e1\u30f3\u30bf\u30ea\u30fc\u00a0\u00a0\u7d20\u4eba", "\r\n\u54c1\u756a\uff1a\u00a0 \u00a0 \u00a0 \u00a0 57jksr00259", "\r\n\r\n"], "text": "[jksr-259]\u7530\u820e\u5a18\u3001\u6642\u7d66696\u5186\u3002\u5e78\u305b\u611b\u4eba\u5951\u7d04", "imgf": "https://www.goldenshark.xyz/images/JKSR-259.jpg", "href": "http://thz2.com/thread-964639-1-190.html", "dlnk": "http://thz2.com/forum.php?mod=attachment&aid=MzU0OTQ0fDZlNDEwMWQyfDE1MjM5MjI1NTl8MHw5NjQ2Mzk%3D"}, {"jref": "http://www.javlibrary.com/en/vl_searchbyid.php?keyword=HUNTA-243", "_type": "dict", "code": "HUNTA-243", "name": "\u3042\u304a\u3044\u308c\u306a", "pdat": ["\r\n\u7247\u540d\uff1a\u8d85\u7d76\u502b\u7ae5\u8c9e\u5c11\u5e74\uff01\u3082\u3046\u30e4\u30e1\u3066\uff01\u3068\u9003\u3052\u308b\u7fa9\u59c9\u3092\u8ffd\u3044\u304b\u3051\u30cf\u30e1\u307e\u304f\u308b\uff014 \u7a81\u7136\u51fa\u6765\u305f\u7fa9\u7406\u306e\u304a\u59c9\u3061\u3083\u3093\u306f\u8d85\u30e4\u30ea\u30de\u30f3\uff01\u3044\u3064\u3082\u8d85\u7121\u9632\u5099\u3060\u304b\u3089\u30d1\u30f3\u30c1\u30e9\u80f8\u30c1\u30e9\u3057\u307e\u304f\u308a\u3067\u30dc\u30af\u306f\u6bce\u65e5\u52c3\u8d77\u3057\u307e\u304f\u308a\uff01\u30dc\u30af\u306e\u52c3\u8d77\u3092\u304b\u3089\u304b\u3046\u304a\u59c9\u3061\u3083\u3093\u3082\u3044\u3064\u3057\u304b\u52c3\u8d77\u306b\u30e0\u30e9\u30e0\u30e9\u3057\u3066\u767a\u60c5\uff01\u6211\u6162\u3067\u304d\u306a\u304f\u306a\u2026", "\r\n\u5bb9\u91cf\uff1a12.9GB", "\r\n\u683c\u5f0f\uff1amp4", "\r\n\u914d\u4fe1\u958b\u59cb\u65e5\uff1a\u00a0 \u00a0 \u00a0 \u00a0 2017/01/02", "\r\n\u5546\u54c1\u767a\u58f2\u65e5\uff1a\u00a0 \u00a0 \u00a0 \u00a0 2017/01/07", "\r\n\u53ce\u9332\u6642\u9593\uff1a\u00a0 \u00a0 \u00a0 \u00a0 444\u5206 \uff08HD\u7248\uff1a444\u5206\uff09", "\r\n\u51fa\u6f14\u8005\uff1a\u00a0 \u00a0 \u00a0 \u00a0 ----", "\r\n\u76e3\u7763\uff1a\u00a0 \u00a0 \u00a0 \u00a0 \u30dc\u30eb\u30dc\u4e2d\u91ce", "\r\n\u30b7\u30ea\u30fc\u30ba\uff1a\u00a0 \u00a0 \u00a0 \u00a0 \u8d85\u7d76\u502b\u7ae5\u8c9e\u5c11\u5e74", "\r\n\u30e1\u30fc\u30ab\u30fc\uff1a\u00a0 \u00a0 \u00a0 \u00a0 Hunter", "\r\n\u30ec\u30fc\u30d9\u30eb\uff1a\u00a0 \u00a0 \u00a0 \u00a0 Hunter\uff08HHH\u30b0\u30eb\u30fc\u30d7\uff09", "\r\n\u30b8\u30e3\u30f3\u30eb\uff1a\u00a0 \u00a0 \u00a0 \u00a0 \u6deb\u4e82?\u30cf\u30fc\u30c9\u7cfb\u00a0\u00a0\u5de8\u4e73\u00a0\u00a04\u6642\u9593\u4ee5\u4e0a\u4f5c\u54c1\u00a0\u00a0\u30d1\u30f3\u30c1\u30e9\u00a0\u00a0\u59c9?\u59b9\u00a0\u00a0\u30cf\u30a4\u30d3\u30b8\u30e7\u30f3\u00a0\u00a0\u7368\u5360\u914d\u4fe1", "\r\n\u54c1\u756a\uff1a\u00a0 \u00a0 \u00a0 \u00a0 hunta00243", "\r\n\r\n"], "text": "[hunta-243]\u8d85\u7d76\u502b\u7ae5\u8c9e\u5c11\u5e74\uff01", "imgf": "https://www.goldenshark.xyz/images/HUNTA-243.jpg", "href": "http://thz2.com/thread-964644-1-190.html", "dlnk": "http://thz2.com/forum.php?mod=attachment&aid=MzU0OTU0fDY1NmRiZTZifDE1MjM5MjI1NjB8MHw5NjQ2NDQ%3D"}, {"jref": "http://www.javlibrary.com/en/vl_searchbyid.php?keyword=DAKS-001", "_type": "dict", "code": "DAKS-001", "name": "\u6589\u85e4\u307f\u3086", "pdat": ["\r\n\u7247\u540d\uff1a\u60aa\u9b54\u306e\u72c2\u4e71\u4e09\u89d2\u6728\u99ac \uff3b\u5b8c\u5168\u64ae\u308a\u4e0b\u308d\u3057\u30aa\u30e0\u30cb\u30d0\u30b9\u00d77\uff3d \u767a\u72c2\u88c5\u7f6e\uff01\u96fb\u30de\uff0b\u304f\u3059\u3050\u308a=\u5730\u7344\u7d75\u56f3", "\r\n\u5bb9\u91cf\uff1a", "\r\n\u683c\u5f0f\uff1amp4", "\r\n\u914d\u4fe1\u958b\u59cb\u65e5\uff1a\u00a0 \u00a0 \u00a0 \u00a0 2016/12/30", "\r\n\u5546\u54c1\u767a\u58f2\u65e5\uff1a\u00a0 \u00a0 \u00a0 \u00a0 2017/01/01", "\r\n\u53ce\u9332\u6642\u9593\uff1a\u00a0 \u00a0 \u00a0 \u00a0 111\u5206 \uff08HD\u7248\uff1a111\u5206\uff09", "\r\n\u51fa\u6f14\u8005\uff1a\u00a0 \u00a0 \u00a0 \u00a0 \u4e00\u689d\u30ea\u30aa\u30f3 \u4f0a\u7e54\u6dbc\u5b50 \u6589\u85e4\u307f\u3086 \u76f8\u6fa4\u3086\u308a\u306a \u6625\u539f\u672a\u4f86 \u9db4\u7530\u304b\u306a \u661f\u5ddd\u9ebb\u7d00", "\r\n\u76e3\u7763\uff1a\u00a0 \u00a0 \u00a0 \u00a0 ----", "\r\n\u30b7\u30ea\u30fc\u30ba\uff1a\u00a0 \u00a0 \u00a0 \u00a0 ----", "\r\n\u30e1\u30fc\u30ab\u30fc\uff1a\u00a0 \u00a0 \u00a0 \u00a0 BabyEntertainment", "\r\n\u30ec\u30fc\u30d9\u30eb\uff1a\u00a0 \u00a0 \u00a0 \u00a0 Baby Entertainment", "\r\n\u30b8\u30e3\u30f3\u30eb\uff1a\u00a0 \u00a0 \u00a0 \u00a0 \u7368\u5360\u914d\u4fe1\u00a0\u00a0\u62d8\u675f\u00a0\u00a0\u7e1b\u308a?\u7dca\u7e1b\u00a0\u00a0\u96fb\u30de", "\r\n\u54c1\u756a\uff1a\u00a0 \u00a0 \u00a0 \u00a0 daks00001", "\r\n\r\n"], "text": "[daks-001]\u60aa\u9b54\u306e\u72c2\u4e71\u4e09\u89d2\u6728\u99ac", "imgf": "https://www.goldenshark.xyz/images/DAKS-001.jpg", "href": "http://thz2.com/thread-964631-1-190.html", "dlnk": "http://thz2.com/forum.php?mod=attachment&aid=MzU0OTMzfGYwMzFjNTlkfDE1MjM5MjI1NjB8MHw5NjQ2MzE%3D"}, {"jref": "http://www.javlibrary.com/en/vl_searchbyid.php?keyword=IPZ-872", "_type": "dict", "code": "IPZ-872", "name": "\u304d\u307f\u304b\u308f\u7d50\u8863", "pdat": ["\r\n\u7247\u540d\uff1a\u3010\u30c7\u30d3\u30e5\u30fc\u524d\u306e\u30c6\u30b9\u30c8\u30cf\u30e1\u64ae\u308a\u6620\u50cf\u53ce\u9332\u3011FIRST IMPRESSION 110 \u30b9\u30bf\u30a4\u30eb\u629c\u7fa4\u306e\u30c4\u30f3\u30c7\u30ec\u7f8e\u4e73\u7f8e\u5973AV\u30c7\u30d3\u30e5\u30fc \u304d\u307f\u304b\u308f\u7d50\u8863", "\r\n\u5bb9\u91cf\uff1a5.56GB", "\r\n\u683c\u5f0f\uff1amp4", "\r\n\u914d\u4fe1\u958b\u59cb\u65e5\uff1a\u00a0 \u00a0 \u00a0 \u00a0 2017/01/01", "\r\n\u5546\u54c1\u767a\u58f2\u65e5\uff1a\u00a0 \u00a0 \u00a0 \u00a0 2017/01/07", "\r\n\u53ce\u9332\u6642\u9593\uff1a\u00a0 \u00a0 \u00a0 \u00a0 191\u5206 \uff08HD\u7248\uff1a191\u5206\uff09", "\r\n\u51fa\u6f14\u8005\uff1a\u00a0 \u00a0 \u00a0 \u00a0 \u304d\u307f\u304b\u308f\u7d50\u8863", "\r\n\u76e3\u7763\uff1a\u00a0 \u00a0 \u00a0 \u00a0 \u30ad\u30e7\u30a6\u30bb\u30a4", "\r\n\u30b7\u30ea\u30fc\u30ba\uff1a\u00a0 \u00a0 \u00a0 \u00a0 First Impression", "\r\n\u30e1\u30fc\u30ab\u30fc\uff1a\u00a0 \u00a0 \u00a0 \u00a0 \u30a2\u30a4\u30c7\u30a2\u30dd\u30b1\u30c3\u30c8", "\r\n\u30ec\u30fc\u30d9\u30eb\uff1a\u00a0 \u00a0 \u00a0 \u00a0 \u30c6\u30a3\u30c3\u30b7\u30e5", "\r\n\u30b8\u30e3\u30f3\u30eb\uff1a\u00a0 \u00a0 \u00a0 \u00a0 \u30cf\u30a4\u30d3\u30b8\u30e7\u30f3\u00a0\u00a0\u7368\u5360\u914d\u4fe1\u00a0\u00a0\u30c7\u30b8\u30e2\u00a0\u00a0\u30cf\u30e1\u64ae\u308a\u00a0\u00a0\u7f8e\u5c11\u5973\u00a0\u00a0\u7f8e\u4e73\u00a0\u00a0\u30c7\u30d3\u30e5\u30fc\u4f5c\u54c1\u00a0\u00a0\u5358\u9ad4\u4f5c\u54c1", "\r\n\u54c1\u756a\uff1a\u00a0 \u00a0 \u00a0 \u00a0 ipz00872", "\r\n\r\n"], "text": "[ipz-872]\u7f8e\u4e73\u7f8e\u5973AV\u30c7\u30d3\u30e5\u30fc \u304d\u307f\u304b\u308f\u7d50\u8863", "imgf": "https://www.goldenshark.xyz/images/IPZ-872.jpg", "href": "http://thz2.com/thread-963788-1-190.html", "dlnk": "http://thz2.com/forum.php?mod=attachment&aid=MzU0ODU5fDhlMmVkNWZkfDE1MjM5MjI1NjF8MHw5NjM3ODg%3D"}, {"jref": "http://www.javlibrary.com/en/vl_searchbyid.php?keyword=IPZ-877", "_type": "dict", "code": "IPZ-877", "name": "\u5929\u6d77\u3064\u3070\u3055", "pdat": ["\r\n\u7247\u540d\uff1a\u4f53\u6db2\u30c0\u30c0\u6f0f\u308c \u30b8\u30e5\u30fc\u30b7\u30fcFUCK G\u30b9\u30dd\u30c3\u30c8\u72d9\u3044\u7a81\u304d\uff01\u5c3f\uff01\u6c57\uff01\u6f6e\uff01\u30cf\u30e1\u6f6e\uff01\u7f8e\u5473\u6c41\u904e\u304e\u308b\u7d76\u9802\u5feb\u697d\uff01 \u5929\u6d77\u3064\u3070\u3055", "\r\n\u5bb9\u91cf\uff1a2.94GB", "\r\n\u683c\u5f0f\uff1amp4", "\r\n\u914d\u4fe1\u958b\u59cb\u65e5\uff1a\u00a0 \u00a0 \u00a0 \u00a0 2017/01/01", "\r\n\u5546\u54c1\u767a\u58f2\u65e5\uff1a\u00a0 \u00a0 \u00a0 \u00a0 2017/01/07", "\r\n\u53ce\u9332\u6642\u9593\uff1a\u00a0 \u00a0 \u00a0 \u00a0 101\u5206 \uff08HD\u7248\uff1a101\u5206\uff09", "\r\n\u51fa\u6f14\u8005\uff1a\u00a0 \u00a0 \u00a0 \u00a0 \u5929\u6d77\u3064\u3070\u3055", "\r\n\u76e3\u7763\uff1a\u00a0 \u00a0 \u00a0 \u00a0 \u3064\u3076\u3084\u304d\u30b8\u30ed\u30fc", "\r\n\u30b7\u30ea\u30fc\u30ba\uff1a\u00a0 \u00a0 \u00a0 \u00a0 ----", "\r\n\u30e1\u30fc\u30ab\u30fc\uff1a\u00a0 \u00a0 \u00a0 \u00a0 \u30a2\u30a4\u30c7\u30a2\u30dd\u30b1\u30c3\u30c8", "\r\n\u30ec\u30fc\u30d9\u30eb\uff1a\u00a0 \u00a0 \u00a0 \u00a0 \u30c6\u30a3\u30c3\u30b7\u30e5", "\r\n\u30b8\u30e3\u30f3\u30eb\uff1a\u00a0 \u00a0 \u00a0 \u00a0 \u30cf\u30a4\u30d3\u30b8\u30e7\u30f3\u00a0\u00a0\u7368\u5360\u914d\u4fe1\u00a0\u00a0\u30c7\u30b8\u30e2\u00a0\u00a0\u5358\u9ad4\u4f5c\u54c1\u00a0\u00a0\u6c57\u3060\u304f\u00a0\u00a0\u6f6e\u5439\u304d\u00a0\u00a0\u304a\u59c9\u3055\u3093\u00a0\u00a0\u653e\u5c3f", "\r\n\u54c1\u756a\uff1a\u00a0 \u00a0 \u00a0 \u00a0 ipz00877", "\r\n\r\n"], "text": "[ipz-877]\u7f8e\u5473\u6c41\u904e\u304e\u308b\u7d76\u9802\u5feb\u697d\uff01 \u5929\u6d77\u3064\u3070\u3055", "imgf": "https://www.goldenshark.xyz/images/IPZ-877.jpg", "href": "http://thz2.com/thread-963792-1-190.html", "dlnk": "http://thz2.com/forum.php?mod=attachment&aid=MzU0ODY3fDI0NzQ3MGVkfDE1MjM5MjI1NjJ8MHw5NjM3OTI%3D"}]