[{"jref": "http://www.javlibrary.com/en/vl_searchbyid.php?keyword=CWM-231", "_type": "dict", "code": "CWM-231", "name": "\u677f\u57a3\u3042\u305a\u3055", "pdat": ["\r\n\u7247\u540d\uff1a\u6d74\u3073\u305f\u5973\u3082\u611f\u6fc0\u3059\u308b\u4e00\u6483\uff01\uff01\u5927\u91cf\u9854\u5c04\uff01\uff01\uff01 Part.5", "\r\n\u5bb9\u91cf\uff1a3.38GB", "\r\n\u683c\u5f0f\uff1amkv", "\r\n\u914d\u4fe1\u958b\u59cb\u65e5\uff1a\u00a0 \u00a0 \u00a0 \u00a0 2015/03/04", "\r\n\u5546\u54c1\u767a\u58f2\u65e5\uff1a\u00a0 \u00a0 \u00a0 \u00a0 2015/03/06", "\r\n\u53ce\u9332\u6642\u9593\uff1a\u00a0 \u00a0 \u00a0 \u00a0 122\u5206 \uff08HD\u7248\uff1a122\u5206\uff09", "\r\n\u51fa\u6f14\u8005\uff1a\u00a0 \u00a0 \u00a0 \u00a0 \u963f\u90e8\u4e43\u307f\u304f \u795e\u6ce2\u591a\u4e00\u82b1 \u84ee\u5b9f\u30af\u30ec\u30a2 \u5e0c\u54b2\u30a8\u30de\uff08HARUKI\u3001\u52a0\u85e4\u306f\u308b\u5e0c\uff09 \u677f\u57a3\u3042\u305a\u3055 \u661f\u5ddd\u9ebb\u7d00 \u671b\u6708\u308b\u306a \u6dbc\u98a8\u3053\u3068\u306e \u3042\u3086\u307f\u7ffc \u677e\u5d8b\u53cb\u91cc\u6075 \u25bc\u3059\u3079\u3066\u8868\u793a\u3059\u308b", "\r\n\u76e3\u7763\uff1a\u00a0 \u00a0 \u00a0 \u00a0 \u4e00\u30ce\u702c\u304f\u308b\u307f", "\r\n\u30b7\u30ea\u30fc\u30ba\uff1a\u00a0 \u00a0 \u00a0 \u00a0 \u6d74\u3073\u305f\u5973\u3082\u611f\u6fc0\u3059\u308b\u4e00\u6483\uff01\uff01\u5927\u91cf\u9854\u5c04\uff01\uff01\uff01", "\r\n\u30e1\u30fc\u30ab\u30fc\uff1a\u00a0 \u00a0 \u00a0 \u00a0 \u30ef\u30fc\u30d7\u30a8\u30f3\u30bf\u30c6\u30a4\u30f3\u30e1\u30f3\u30c8", "\r\n\u30ec\u30fc\u30d9\u30eb\uff1a\u00a0 \u00a0 \u00a0 \u00a0 Washing machine", "\r\n\u30b8\u30e3\u30f3\u30eb\uff1a\u00a0 \u00a0 \u00a0 \u00a0 \u9854\u5c04\u00a0\u00a0\u4f01\u756b\u00a0\u00a0\u3076\u3063\u304b\u3051\u00a0\u00a0\u30cf\u30a4\u30d3\u30b8\u30e7\u30f3", "\r\n\u54c1\u756a\uff1a\u00a0 \u00a0 \u00a0 \u00a0 2cwm00231", "\r\n\r\n"], "text": "[CWM-231]\u6d74\u3073\u305f\u5973\u3082\u611f\u6fc0\u3059\u308b\u4e00\u6483\uff01\uff01\u5927\u91cf\u9854\u5c04\uff01\uff01\uff01 Part.5", "imgf": "https://www.goldenshark.xyz/images/CWM-231.jpg", "href": "http://thz2.com/thread-296079-1-318.html", "dlnk": "http://thz2.com/forum.php?mod=attachment&aid=MjUzMjQ5fDIwMGIyOThifDE1MjM5MjMzODJ8MHwyOTYwNzk%3D"}, {"jref": "http://www.javlibrary.com/en/vl_searchbyid.php?keyword=BF-371", "_type": "dict", "code": "BF-371", "name": "\u6ce2\u591a\u91ce\u7ed3\u8863", "pdat": ["\r\n\u7247\u540d\uff1a\u30dc\u30f3\u30c7\u30fc\u30b8\u30ac\u30fc\u30eb \u8d85\u7d76\u75d9\u6523SEX \u6ce2\u591a\u91ce\u7d50\u8863", "\r\n\u5bb9\u91cf\uff1a3.25GB", "\r\n\u683c\u5f0f\uff1amkv", "\r\n\u914d\u4fe1\u958b\u59cb\u65e5\uff1a\u00a0 \u00a0 \u00a0 \u00a0 2015/03/05", "\r\n\u5546\u54c1\u767a\u58f2\u65e5\uff1a\u00a0 \u00a0 \u00a0 \u00a0 2015/03/07", "\r\n\u53ce\u9332\u6642\u9593\uff1a\u00a0 \u00a0 \u00a0 \u00a0 118\u5206 \uff08HD\u7248\uff1a118\u5206\uff09", "\r\n\u51fa\u6f14\u8005\uff1a\u00a0 \u00a0 \u00a0 \u00a0 \u6ce2\u591a\u91ce\u7d50\u8863", "\r\n\u76e3\u7763\uff1a\u00a0 \u00a0 \u00a0 \u00a0 \u3070\u3063\u3066\u3093\u4e5d\u5dde\u7537", "\r\n\u30b7\u30ea\u30fc\u30ba\uff1a\u00a0 \u00a0 \u00a0 \u00a0 \u30dc\u30f3\u30c7\u30fc\u30b8\u30ac\u30fc\u30eb", "\r\n\u30e1\u30fc\u30ab\u30fc\uff1a\u00a0 \u00a0 \u00a0 \u00a0 BeFree", "\r\n\u30ec\u30fc\u30d9\u30eb\uff1a\u00a0 \u00a0 \u00a0 \u00a0 BeFree", "\r\n\u30b8\u30e3\u30f3\u30eb\uff1a\u00a0 \u00a0 \u00a0 \u00a0 \u30dc\u30f3\u30c6\u30fc\u30b8\u00a0\u00a0\u30c9\u30ad\u30e5\u30e1\u30f3\u30bf\u30ea\u30fc\u00a0\u00a0\u5358\u9ad4\u4f5c\u54c1\u00a0\u00a0\u7368\u5360\u914d\u4fe1\u00a0\u00a0\u30cf\u30a4\u30d3\u30b8\u30e7\u30f3\u00a0\u00a0DVD\u30c8\u30fc\u30b9\u30bf\u30fc", "\r\n\u54c1\u756a\uff1a\u00a0 \u00a0 \u00a0 \u00a0 bf00371", "\r\n\r\n"], "text": "[BF-371]\u30dc\u30f3\u30c7\u30fc\u30b8\u30ac\u30fc\u30eb \u8d85\u7d76\u75d9\u6523SEX \u6ce2\u591a\u91ce\u7d50\u8863", "imgf": "https://www.goldenshark.xyz/images/BF-371.jpg", "href": "http://thz2.com/thread-299003-1-318.html", "dlnk": "http://thz2.com/forum.php?mod=attachment&aid=MjUzNjU1fDk1ZDkyMmVifDE1MjM5MjMzODJ8MHwyOTkwMDM%3D"}, {"jref": "http://www.javlibrary.com/en/vl_searchbyid.php?keyword=GM-016", "_type": "dict", "code": "GM-016", "name": "\u5c0f\u5ddd\u3081\u308b\u308b", "pdat": ["\r\n\u7247\u540d\uff1a\u96c4\u4e8c\u30b4\u30e1\u30b9loves 016 \u307e\u308a\u3061\u3083\u30931\u25cf\u624d\u51e6\u5973", "\r\n\u5bb9\u91cf\uff1a2.03Gb", "\r\n\u683c\u5f0f\uff1amkv", "\r\n\u914d\u4fe1\u958b\u59cb\u65e5\uff1a\u00a0 \u00a0 \u00a0 \u00a0 2015/03/03", "\r\n\u5546\u54c1\u767a\u58f2\u65e5\uff1a\u00a0 \u00a0 \u00a0 \u00a0 2015/03/01", "\r\n\u53ce\u9332\u6642\u9593\uff1a\u00a0 \u00a0 \u00a0 \u00a0 146\u5206", "\r\n\u51fa\u6f14\u8005\uff1a\u00a0 \u00a0 \u00a0 \u00a0 ----", "\r\n\u76e3\u7763\uff1a\u00a0 \u00a0 \u00a0 \u00a0 \u3072\u3080\u308d\u3063\u304f", "\r\n\u30b7\u30ea\u30fc\u30ba\uff1a\u00a0 \u00a0 \u00a0 \u00a0 \u96c4\u4e8c\u30b4\u30e1\u30b9loves", "\r\n\u30e1\u30fc\u30ab\u30fc\uff1a\u00a0 \u00a0 \u00a0 \u00a0 \u30d7\u30e9\u30e0", "\r\n\u30ec\u30fc\u30d9\u30eb\uff1a\u00a0 \u00a0 \u00a0 \u00a0 Sugar PLUM", "\r\n\u30b8\u30e3\u30f3\u30eb\uff1a\u00a0 \u00a0 \u00a0 \u00a0 \u7d20\u4eba\u00a0\u00a0\u51e6\u5973\u00a0\u00a0\u30d5\u30a7\u30e9", "\r\n\u54c1\u756a\uff1a\u00a0 \u00a0 \u00a0 \u00a0 h_113gm00016", "\r\n\r\n"], "text": "[GM-016]\u96c4\u4e8c\u30b4\u30e1\u30b9loves 016 \u307e\u308a\u3061\u3083\u30931\u25cf\u624d\u51e6\u5973", "imgf": "https://www.goldenshark.xyz/images/GM-016.jpg", "href": "http://thz2.com/thread-299014-1-318.html", "dlnk": "http://thz2.com/forum.php?mod=attachment&aid=MjUzNjYxfDJiMmNlNmZifDE1MjM5MjMzODN8MHwyOTkwMTQ%3D"}, {"jref": "http://www.javlibrary.com/en/vl_searchbyid.php?keyword=MXGS-742", "_type": "dict", "code": "MXGS-742", "name": "\u9ebb\u751f\u5e0c", "pdat": ["\r\n\u7247\u540d\uff1a\u30a4\u30ad\u307e\u304f\u308b\u7d76\u9802\u5973\u795e\u3002 \u9ebb\u751f\u5e0c \u30d1\u30f3\u30c6\u30a3\u3068\u30c1\u30a7\u30ad\u4ed8\u304d", "\r\n\u5bb9\u91cf\uff1a1.72Gb", "\r\n\u683c\u5f0f\uff1amkv", "\r\n\u767a\u58f2\u65e5\uff1a\u00a0 \u00a0 \u00a0 \u00a0 2015/03/16", "\r\n\u53ce\u9332\u6642\u9593\uff1a\u00a0 \u00a0 \u00a0 \u00a0 120\u5206", "\r\n\u51fa\u6f14\u8005\uff1a\u00a0 \u00a0 \u00a0 \u00a0 \u9ebb\u751f\u5e0c", "\r\n\u76e3\u7763\uff1a\u00a0 \u00a0 \u00a0 \u00a0 \u30c7\u30e93", "\r\n\u30b7\u30ea\u30fc\u30ba\uff1a\u00a0 \u00a0 \u00a0 \u00a0 \u30a4\u30ad\u307e\u304f\u308b\u7d76\u9802\u5973\u795e\u3002", "\r\n\u30e1\u30fc\u30ab\u30fc\uff1a\u00a0 \u00a0 \u00a0 \u00a0 \u30de\u30ad\u30b7\u30f3\u30b0", "\r\n\u30ec\u30fc\u30d9\u30eb\uff1a\u00a0 \u00a0 \u00a0 \u00a0 MAXING", "\r\n\u30b8\u30e3\u30f3\u30eb\uff1a\u00a0 \u00a0 \u00a0 \u00a0 \u9577\u8eab \u5358\u9ad4\u4f5c\u54c1 \u4e2d\u51fa\u3057 \u304a\u3082\u3061\u3083 3P?4P \u30a4\u30e9\u30de\u30c1\u30aa \u7279\u5178\u5bfe\u8c61", "\r\n\u54c1\u756a\uff1a\u00a0 \u00a0 \u00a0 \u00a0 h_068mxgs742tk", "\r\n\r\n"], "text": "[MXGS-742]\u30a4\u30ad\u307e\u304f\u308b\u7d76\u9802\u5973\u795e\u3002 \u9ebb\u751f\u5e0c \u30d1\u30f3\u30c6\u30a3\u3068\u30c1\u30a7\u30ad\u4ed8\u304d", "imgf": "https://www.goldenshark.xyz/images/MXGS-742.jpg", "href": "http://thz2.com/thread-299049-1-318.html", "dlnk": "http://thz2.com/forum.php?mod=attachment&aid=MjUzNjczfGY0OWVkMGNjfDE1MjM5MjMzODR8MHwyOTkwNDk%3D"}, {"jref": "http://www.javlibrary.com/en/vl_searchbyid.php?keyword=WANZ-312", "_type": "dict", "code": "WANZ-312", "name": "\u996d\u5188\u52a0\u5948\u5b50", "pdat": ["\r\n\u7247\u540d\uff1a\u79c1\u306e\u5b50\u5bae\u3092\u5c04\u7cbe\u3067\u30aa\u3068\u3057\u3066 \u98ef\u5ca1\u304b\u306a\u3053", "\r\n\u5bb9\u91cf\uff1a3.28Gb", "\r\n\u683c\u5f0f\uff1amkv", "\r\n\u914d\u4fe1\u958b\u59cb\u65e5\uff1a\u00a0 \u00a0 \u00a0 \u00a0 2015/02/28", "\r\n\u5546\u54c1\u767a\u58f2\u65e5\uff1a\u00a0 \u00a0 \u00a0 \u00a0 2015/03/01", "\r\n\u53ce\u9332\u6642\u9593\uff1a\u00a0 \u00a0 \u00a0 \u00a0 119\u5206 \uff08HD\u7248\uff1a119\u5206\uff09", "\r\n\u51fa\u6f14\u8005\uff1a\u00a0 \u00a0 \u00a0 \u00a0 \u98ef\u5ca1\u304b\u306a\u3053", "\r\n\u76e3\u7763\uff1a\u00a0 \u00a0 \u00a0 \u00a0 ----", "\r\n\u30b7\u30ea\u30fc\u30ba\uff1a\u00a0 \u00a0 \u00a0 \u00a0 \u79c1\u306e\u5b50\u5bae\u3092\u5c04\u7cbe\u3067\u30aa\u3068\u3057\u3066", "\r\n\u30e1\u30fc\u30ab\u30fc\uff1a\u00a0 \u00a0 \u00a0 \u00a0 \u30ef\u30f3\u30ba\u30d5\u30a1\u30af\u30c8\u30ea\u30fc", "\r\n\u30ec\u30fc\u30d9\u30eb\uff1a\u00a0 \u00a0 \u00a0 \u00a0 WANZ", "\r\n\u30b8\u30e3\u30f3\u30eb\uff1a\u00a0 \u00a0 \u00a0 \u00a0 \u4e2d\u51fa\u3057\u00a0\u00a0\u6deb\u8a9e\u00a0\u00a0\u304a\u59c9\u3055\u3093\u00a0\u00a0\u30b9\u30ec\u30f3\u30c0\u30fc\u00a0\u00a0\u5358\u9ad4\u4f5c\u54c1\u00a0\u00a0\u7368\u5360\u914d\u4fe1\u00a0\u00a0\u30cf\u30a4\u30d3\u30b8\u30e7\u30f3\u00a0\u00a0DVD\u30c8\u30fc\u30b9\u30bf\u30fc", "\r\n\u54c1\u756a\uff1a\u00a0 \u00a0 \u00a0 \u00a0 wanz00312", "\r\n\r\n"], "text": "[WANZ-312]\u79c1\u306e\u5b50\u5bae\u3092\u5c04\u7cbe\u3067\u30aa\u3068\u3057\u3066 \u98ef\u5ca1\u304b\u306a\u3053", "imgf": "https://www.goldenshark.xyz/images/WANZ-312.jpg", "href": "http://thz2.com/thread-294109-1-319.html", "dlnk": "http://thz2.com/forum.php?mod=attachment&aid=MjUzMDYxfDczYmYwNWExfDE1MjM5MjMzODV8MHwyOTQxMDk%3D"}, {"jref": "http://www.javlibrary.com/en/vl_searchbyid.php?keyword=MIDE-205", "_type": "dict", "code": "MIDE-205", "name": "\u79cb\u5c71\u7965\u5b50", "pdat": ["\r\n\u7247\u540d\uff1a\u72af\u3055\u308c\u305f\u7f8e\u811aRQ \u79cb\u5c71\u7965\u5b50", "\r\n\u5bb9\u91cf\uff1a4.12Gb", "\r\n\u683c\u5f0f\uff1amkv", "\r\n\u914d\u4fe1\u958b\u59cb\u65e5\uff1a\u00a0 \u00a0 \u00a0 \u00a0 2015/02/28", "\r\n\u5546\u54c1\u767a\u58f2\u65e5\uff1a\u00a0 \u00a0 \u00a0 \u00a0 2015/03/01", "\r\n\u53ce\u9332\u6642\u9593\uff1a\u00a0 \u00a0 \u00a0 \u00a0 149\u5206 \uff08HD\u7248\uff1a149\u5206\uff09", "\r\n\u51fa\u6f14\u8005\uff1a\u00a0 \u00a0 \u00a0 \u00a0 \u79cb\u5c71\u7965\u5b50", "\r\n\u76e3\u7763\uff1a\u00a0 \u00a0 \u00a0 \u00a0 \u5b87\u4f50\u7f8e\u5fe0\u5247", "\r\n\u30b7\u30ea\u30fc\u30ba\uff1a\u00a0 \u00a0 \u00a0 \u00a0 ----", "\r\n\u30e1\u30fc\u30ab\u30fc\uff1a\u00a0 \u00a0 \u00a0 \u00a0 \u30e0\u30fc\u30c7\u30a3\u30fc\u30ba", "\r\n\u30ec\u30fc\u30d9\u30eb\uff1a\u00a0 \u00a0 \u00a0 \u00a0 MOODYZ DIVA", "\r\n\u30b8\u30e3\u30f3\u30eb\uff1a\u00a0 \u00a0 \u00a0 \u00a0 \u5358\u9ad4\u4f5c\u54c1\u00a0\u00a0\u8fb1\u3081\u00a0\u00a0\u7f8e\u5c11\u5973\u00a0\u00a0\u4e82\u4ea4\u00a0\u00a0\u3076\u3063\u304b\u3051\u00a0\u00a0\u30c7\u30b8\u30e2\u00a0\u00a0\u7368\u5360\u914d\u4fe1\u00a0\u00a0\u30cf\u30a4\u30d3\u30b8\u30e7\u30f3", "\r\n\u54c1\u756a\uff1a\u00a0 \u00a0 \u00a0 \u00a0 mide00205", "\r\n\r\n"], "text": "[MIDE-205]\u72af\u3055\u308c\u305f\u7f8e\u811aRQ \u79cb\u5c71\u7965\u5b50", "imgf": "https://www.goldenshark.xyz/images/MIDE-205.jpg", "href": "http://thz2.com/thread-294027-1-319.html", "dlnk": "http://thz2.com/forum.php?mod=attachment&aid=MjUzMDMwfDUxYTg4MGNkfDE1MjM5MjMzODV8MHwyOTQwMjc%3D"}, {"jref": "http://www.javlibrary.com/en/vl_searchbyid.php?keyword=WANZ-307", "_type": "dict", "code": "WANZ-307", "name": "\u9ebb\u5009\u6182", "pdat": ["\r\n\u7247\u540d\uff1a\u65b0\u4efb\u5973\u6559\u5e2b \u6b8b\u5fcd\u51b7\u9177\u4e2d\u51fa\u3057\u30ec\u00d7\u30d7\u8f2a\u59e6 \u9ebb\u5009\u6182", "\r\n\u5bb9\u91cf\uff1a3.28Gb", "\r\n\u683c\u5f0f\uff1amkv", "\r\n\u914d\u4fe1\u958b\u59cb\u65e5\uff1a\u00a0 \u00a0 \u00a0 \u00a0 2015/02/28", "\r\n\u5546\u54c1\u767a\u58f2\u65e5\uff1a\u00a0 \u00a0 \u00a0 \u00a0 2015/03/01", "\r\n\u53ce\u9332\u6642\u9593\uff1a\u00a0 \u00a0 \u00a0 \u00a0 119\u5206 \uff08HD\u7248\uff1a119\u5206\uff09", "\r\n\u51fa\u6f14\u8005\uff1a\u00a0 \u00a0 \u00a0 \u00a0 \u9ebb\u5009\u6182", "\r\n\u76e3\u7763\uff1a\u00a0 \u00a0 \u00a0 \u00a0 ----", "\r\n\u30b7\u30ea\u30fc\u30ba\uff1a\u00a0 \u00a0 \u00a0 \u00a0 ----", "\r\n\u30e1\u30fc\u30ab\u30fc\uff1a\u00a0 \u00a0 \u00a0 \u00a0 \u30ef\u30f3\u30ba\u30d5\u30a1\u30af\u30c8\u30ea\u30fc", "\r\n\u30ec\u30fc\u30d9\u30eb\uff1a\u00a0 \u00a0 \u00a0 \u00a0 WANZ", "\r\n\u30b8\u30e3\u30f3\u30eb\uff1a\u00a0 \u00a0 \u00a0 \u00a0 \u30cf\u30a4\u30d3\u30b8\u30e7\u30f3\u00a0\u00a0\u8f2a\u59e6\u00a0\u00a0\u4e2d\u51fa\u3057\u00a0\u00a0\u5973\u6559\u5e2b\u00a0\u00a0\u5f37\u59e6\u00a0\u00a0\u8fb1\u3081\u00a0\u00a0\u5358\u9ad4\u4f5c\u54c1\u00a0\u00a0\u7368\u5360\u914d\u4fe1\u00a0\u00a0DVD\u30c8\u30fc\u30b9\u30bf\u30fc", "\r\n\u54c1\u756a\uff1a\u00a0 \u00a0 \u00a0 \u00a0 wanz00307", "\r\n\r\n"], "text": "[WANZ-307]\u65b0\u4efb\u5973\u6559\u5e2b \u6b8b\u5fcd\u51b7\u9177\u4e2d\u51fa\u3057\u30ec\u00d7\u30d7\u8f2a\u59e6 \u9ebb\u5009\u6182", "imgf": "https://www.goldenshark.xyz/images/WANZ-307.jpg", "href": "http://thz2.com/thread-294091-1-319.html", "dlnk": "http://thz2.com/forum.php?mod=attachment&aid=MjUzMDUxfDk5ZjJjYjJjfDE1MjM5MjMzODZ8MHwyOTQwOTE%3D"}, {"jref": "http://www.javlibrary.com/en/vl_searchbyid.php?keyword=WANZ-310", "_type": "dict", "code": "WANZ-310", "name": "\u88d5\u6728\u307e\u3086", "pdat": ["\r\n\u7247\u540d\uff1a\u65e9\u6f0f\u6539\u5584\u4e2d\u51fa\u3057OK\uff01\u30bd\u30fc\u30d7\u30e9\u30f3\u30c9 \u88d5\u6728\u307e\u3086", "\r\n\u5bb9\u91cf\uff1a4.23Gb", "\r\n\u683c\u5f0f\uff1amkv", "\r\n\u914d\u4fe1\u958b\u59cb\u65e5\uff1a\u00a0 \u00a0 \u00a0 \u00a0 2015/02/28", "\r\n\u5546\u54c1\u767a\u58f2\u65e5\uff1a\u00a0 \u00a0 \u00a0 \u00a0 2015/03/01", "\r\n\u53ce\u9332\u6642\u9593\uff1a\u00a0 \u00a0 \u00a0 \u00a0 153\u5206 \uff08HD\u7248\uff1a153\u5206\uff09", "\r\n\u51fa\u6f14\u8005\uff1a\u00a0 \u00a0 \u00a0 \u00a0 \u88d5\u6728\u307e\u3086", "\r\n\u76e3\u7763\uff1a\u00a0 \u00a0 \u00a0 \u00a0 ----", "\r\n\u30b7\u30ea\u30fc\u30ba\uff1a\u00a0 \u00a0 \u00a0 \u00a0 ----", "\r\n\u30e1\u30fc\u30ab\u30fc\uff1a\u00a0 \u00a0 \u00a0 \u00a0 \u30ef\u30f3\u30ba\u30d5\u30a1\u30af\u30c8\u30ea\u30fc", "\r\n\u30ec\u30fc\u30d9\u30eb\uff1a\u00a0 \u00a0 \u00a0 \u00a0 WANZ", "\r\n\u30b8\u30e3\u30f3\u30eb\uff1a\u00a0 \u00a0 \u00a0 \u00a0 \u30ad\u30e3\u30d0\u5b22?\u98a8\u4fd7\u5b22\u00a0\u00a0\u4e2d\u51fa\u3057\u00a0\u00a0\u304a\u59c9\u3055\u3093\u00a0\u00a0\u7661\u5973\u00a0\u00a0\u624b\u30b3\u30ad\u00a0\u00a0\u5358\u9ad4\u4f5c\u54c1\u00a0\u00a0\u7368\u5360\u914d\u4fe1\u00a0\u00a0\u30cf\u30a4\u30d3\u30b8\u30e7\u30f3", "\r\n\u54c1\u756a\uff1a\u00a0 \u00a0 \u00a0 \u00a0 wanz00310", "\r\n\r\n"], "text": "[WANZ-310]\u65e9\u6f0f\u6539\u5584\u4e2d\u51fa\u3057OK\uff01\u30bd\u30fc\u30d7\u30e9\u30f3\u30c9 \u88d5\u6728\u307e\u3086", "imgf": "https://www.goldenshark.xyz/images/WANZ-310.jpg", "href": "http://thz2.com/thread-294104-1-319.html", "dlnk": "http://thz2.com/forum.php?mod=attachment&aid=MjUzMDU3fGU3ZmNhZWJlfDE1MjM5MjMzODZ8MHwyOTQxMDQ%3D"}, {"jref": "http://www.javlibrary.com/en/vl_searchbyid.php?keyword=WANZ-311", "_type": "dict", "code": "WANZ-311", "name": "\u3064\u307c\u307f", "pdat": ["\r\n\u7247\u540d\uff1a\u79c1\u306e\u5f31\u70b9\u304c\u5468\u308a\u306e\u4eba\u306b\u3070\u308c\u3066\u307e\u3059\u3002 \u3064\u307c\u307f", "\r\n\u5bb9\u91cf\uff1a3.20Gb", "\r\n\u683c\u5f0f\uff1amkv", "\r\n\u914d\u4fe1\u958b\u59cb\u65e5\uff1a\u00a0 \u00a0 \u00a0 \u00a0 2015/02/28", "\r\n\u5546\u54c1\u767a\u58f2\u65e5\uff1a\u00a0 \u00a0 \u00a0 \u00a0 2015/03/01", "\r\n\u53ce\u9332\u6642\u9593\uff1a\u00a0 \u00a0 \u00a0 \u00a0 116\u5206 \uff08HD\u7248\uff1a116\u5206\uff09", "\r\n\u51fa\u6f14\u8005\uff1a\u00a0 \u00a0 \u00a0 \u00a0 \u3064\u307c\u307f", "\r\n\u76e3\u7763\uff1a\u00a0 \u00a0 \u00a0 \u00a0 ----", "\r\n\u30b7\u30ea\u30fc\u30ba\uff1a\u00a0 \u00a0 \u00a0 \u00a0 ----", "\r\n\u30e1\u30fc\u30ab\u30fc\uff1a\u00a0 \u00a0 \u00a0 \u00a0 \u30ef\u30f3\u30ba\u30d5\u30a1\u30af\u30c8\u30ea\u30fc", "\r\n\u30ec\u30fc\u30d9\u30eb\uff1a\u00a0 \u00a0 \u00a0 \u00a0 WANZ", "\r\n\u30b8\u30e3\u30f3\u30eb\uff1a\u00a0 \u00a0 \u00a0 \u00a0 \u5be2\u53d6\u308a?\u5be2\u53d6\u3089\u308c\u00a0\u00a0\u4e2d\u51fa\u3057\u00a0\u00a0\u82b1\u5ac1?\u82e5\u59bb\u00a0\u00a0\u6deb\u8a9e\u00a0\u00a0\u5358\u9ad4\u4f5c\u54c1\u00a0\u00a0\u7368\u5360\u914d\u4fe1\u00a0\u00a0\u30cf\u30a4\u30d3\u30b8\u30e7\u30f3\u00a0\u00a0DVD\u30c8\u30fc\u30b9\u30bf\u30fc", "\r\n\u54c1\u756a\uff1a\u00a0 \u00a0 \u00a0 \u00a0 wanz00311", "\r\n\r\n"], "text": "[WANZ-311]\u79c1\u306e\u5f31\u70b9\u304c\u5468\u308a\u306e\u4eba\u306b\u3070\u308c\u3066\u307e\u3059\u3002 \u3064\u307c\u307f", "imgf": "https://www.goldenshark.xyz/images/WANZ-311.jpg", "href": "http://thz2.com/thread-294108-1-319.html", "dlnk": "http://thz2.com/forum.php?mod=attachment&aid=MjUzMDU5fGY3MmNiNjM1fDE1MjM5MjMzODd8MHwyOTQxMDg%3D"}, {"jref": "http://www.javlibrary.com/en/vl_searchbyid.php?keyword=IPZ-536", "_type": "dict", "code": "IPZ-536", "name": "Rio", "pdat": ["\r\n\u7247\u540d\uff1a\u9023\u7d9a\u5c04\u7cbe\u3057\u3066\u3057\u307e\u3046\u307b\u3069\u904e\u6fc0\u306a\u6027\u4ea4 Rio", "\r\n\u5bb9\u91cf\uff1a4.54Gb", "\r\n\u683c\u5f0f\uff1amkv", "\r\n\u914d\u4fe1\u958b\u59cb\u65e5\uff1a\u00a0 \u00a0 \u00a0 \u00a0 2015/02/28", "\r\n\u5546\u54c1\u767a\u58f2\u65e5\uff1a\u00a0 \u00a0 \u00a0 \u00a0 2015/03/01", "\r\n\u53ce\u9332\u6642\u9593\uff1a\u00a0 \u00a0 \u00a0 \u00a0 164\u5206 \uff08HD\u7248\uff1a164\u5206\uff09", "\r\n\u51fa\u6f14\u8005\uff1a\u00a0 \u00a0 \u00a0 \u00a0 Rio\uff08\u67da\u6728\u30c6\u30a3\u30ca\uff09", "\r\n\u76e3\u7763\uff1a\u00a0 \u00a0 \u00a0 \u00a0 \u897f\u91ce\u30ab\u30ef", "\r\n\u30b7\u30ea\u30fc\u30ba\uff1a\u00a0 \u00a0 \u00a0 \u00a0 \u9023\u7d9a\u5c04\u7cbe\u3057\u3066\u3057\u307e\u3046\u307b\u3069\u904e\u6fc0\u306a\u6027\u4ea4", "\r\n\u30e1\u30fc\u30ab\u30fc\uff1a\u00a0 \u00a0 \u00a0 \u00a0 \u30a2\u30a4\u30c7\u30a2\u30dd\u30b1\u30c3\u30c8", "\r\n\u30ec\u30fc\u30d9\u30eb\uff1a\u00a0 \u00a0 \u00a0 \u00a0 \u30c6\u30a3\u30c3\u30b7\u30e5", "\r\n\u30b8\u30e3\u30f3\u30eb\uff1a\u00a0 \u00a0 \u00a0 \u00a0 \u30c7\u30b8\u30e2\u00a0\u00a0\u7661\u5973\u00a0\u00a0\u304a\u59c9\u3055\u3093\u00a0\u00a0\u5358\u9ad4\u4f5c\u54c1\u00a0\u00a0\u6f6e\u5439\u304d\u00a0\u00a0\u7368\u5360\u914d\u4fe1\u00a0\u00a0\u30cf\u30a4\u30d3\u30b8\u30e7\u30f3", "\r\n\u54c1\u756a\uff1a\u00a0 \u00a0 \u00a0 \u00a0 ipz00536", "\r\n\r\n"], "text": "[IPZ-536]\u9023\u7d9a\u5c04\u7cbe\u3057\u3066\u3057\u307e\u3046\u307b\u3069\u904e\u6fc0\u306a\u6027\u4ea4 Rio", "imgf": "https://www.goldenshark.xyz/images/IPZ-536.jpg", "href": "http://thz2.com/thread-289491-1-319.html", "dlnk": "http://thz2.com/forum.php?mod=attachment&aid=MjUyNjI3fDg5MTFhOGY3fDE1MjM5MjMzODd8MHwyODk0OTE%3D"}, {"jref": "http://www.javlibrary.com/en/vl_searchbyid.php?keyword=ZUKO-072", "_type": "dict", "code": "ZUKO-072", "name": "\u3042\u3079\u307f\u304b\u3053", "pdat": ["\r\n\u7247\u540d\uff1a\u5236\u670d\u5973\u5b50\u6821\u751f\u3068\u4e2d\u51fa\u3057\u4e71\u4ea4\uff5e\u5352\u696d\uff5e", "\r\n\u5bb9\u91cf\uff1a4.96Gb", "\r\n\u683c\u5f0f\uff1amkv", "\r\n\u914d\u4fe1\u958b\u59cb\u65e5\uff1a\u00a0 \u00a0 \u00a0 \u00a0 2015/02/28", "\r\n\u5546\u54c1\u767a\u58f2\u65e5\uff1a\u00a0 \u00a0 \u00a0 \u00a0 2015/03/01", "\r\n\u53ce\u9332\u6642\u9593\uff1a\u00a0 \u00a0 \u00a0 \u00a0 179\u5206 \uff08HD\u7248\uff1a179\u5206\uff09", "\r\n\u51fa\u6f14\u8005\uff1a\u00a0 \u00a0 \u00a0 \u00a0 \u9752\u6728\u307f\u3086 \u592a\u7530\u307e\u307f \u3042\u3079\u307f\u304b\u3053 \u771f\u91ce\u3086\u308a\u3042 \u6e0b\u8c37\u7f8e\u5e0c \u7267\u702c\u611b", "\r\n\u76e3\u7763\uff1a\u00a0 \u00a0 \u00a0 \u00a0 \u3089\u304f\u3060", "\r\n\u30b7\u30ea\u30fc\u30ba\uff1a\u00a0 \u00a0 \u00a0 \u00a0 \u5236\u670d\u5973\u5b50\u6821\u751f\u3068\u4e2d\u51fa\u3057\u4e82\u4ea4", "\r\n\u30e1\u30fc\u30ab\u30fc\uff1a\u00a0 \u00a0 \u00a0 \u00a0 \u30ba\u30c3\u30b3\u30f3/\u30d0\u30c3\u30b3\u30f3", "\r\n\u30ec\u30fc\u30d9\u30eb\uff1a\u00a0 \u00a0 \u00a0 \u00a0 \u30ba\u30c3\u30b3\u30f3/\u30d0\u30c3\u30b3\u30f3", "\r\n\u30b8\u30e3\u30f3\u30eb\uff1a\u00a0 \u00a0 \u00a0 \u00a0 \u5973\u5b50\u6821\u751f\u00a0\u00a0\u4e82\u4ea4\u00a0\u00a0\u7f8e\u5c11\u5973\u00a0\u00a0\u4e2d\u51fa\u3057\u00a0\u00a0\u5b78\u751f\u670d\u00a0\u00a0\u7368\u5360\u914d\u4fe1\u00a0\u00a0\u30cf\u30a4\u30d3\u30b8\u30e7\u30f3", "\r\n\u54c1\u756a\uff1a\u00a0 \u00a0 \u00a0 \u00a0 zuko00072", "\r\n\r\n"], "text": "[ZUKO-072]\u5236\u670d\u5973\u5b50\u6821\u751f\u3068\u4e2d\u51fa\u3057\u4e71\u4ea4\uff5e\u5352\u696d\uff5e", "imgf": "https://www.goldenshark.xyz/images/ZUKO-072.jpg", "href": "http://thz2.com/thread-294006-1-319.html", "dlnk": "http://thz2.com/forum.php?mod=attachment&aid=MjUzMDIyfDIyYTE4OGFhfDE1MjM5MjMzODh8MHwyOTQwMDY%3D"}, {"jref": "http://www.javlibrary.com/en/vl_searchbyid.php?keyword=ZUKO-073", "_type": "dict", "code": "ZUKO-073", "name": "\u5bae\u5185\u681e", "pdat": ["\r\n\u7247\u540d\uff1a\u5144\u8cb4\u306e\u5a18\u9054\u304c\u30a8\u30ed\u304f\u4ed5\u8fbc\u307e\u308c\u3066\u3066\u5b50\u4f5c\u308a", "\r\n\u5bb9\u91cf\uff1a3.25Gb", "\r\n\u683c\u5f0f\uff1amkv", "\r\n\u914d\u4fe1\u958b\u59cb\u65e5\uff1a\u00a0 \u00a0 \u00a0 \u00a0 2015/02/28", "\r\n\u5546\u54c1\u767a\u58f2\u65e5\uff1a\u00a0 \u00a0 \u00a0 \u00a0 2015/03/01", "\r\n\u53ce\u9332\u6642\u9593\uff1a\u00a0 \u00a0 \u00a0 \u00a0 118\u5206 \uff08HD\u7248\uff1a118\u5206\uff09", "\r\n\u51fa\u6f14\u8005\uff1a\u00a0 \u00a0 \u00a0 \u00a0 \u52a0\u8cc0\u7f8e\u30b7\u30e5\u30ca \u5409\u4e95\u3042\u308a\u3055 \u590f\u6d77\u3044\u304f \u5bae\u5167\u681e", "\r\n\u76e3\u7763\uff1a\u00a0 \u00a0 \u00a0 \u00a0 \u3089\u304f\u3060", "\r\n\u30b7\u30ea\u30fc\u30ba\uff1a\u00a0 \u00a0 \u00a0 \u00a0 ----", "\r\n\u30e1\u30fc\u30ab\u30fc\uff1a\u00a0 \u00a0 \u00a0 \u00a0 \u30ba\u30c3\u30b3\u30f3/\u30d0\u30c3\u30b3\u30f3", "\r\n\u30ec\u30fc\u30d9\u30eb\uff1a\u00a0 \u00a0 \u00a0 \u00a0 \u30ba\u30c3\u30b3\u30f3/\u30d0\u30c3\u30b3\u30f3", "\r\n\u30b8\u30e3\u30f3\u30eb\uff1a\u00a0 \u00a0 \u00a0 \u00a0 \u30ed\u30ea\u7cfb\u00a0\u00a0\u4e82\u4ea4\u00a0\u00a0\u30df\u30cb\u7cfb?\u5c0f\u67c4\u00a0\u00a0\u4e2d\u51fa\u3057\u00a0\u00a0\u30d1\u30a4\u30d1\u30f3\u00a0\u00a0\u7368\u5360\u914d\u4fe1\u00a0\u00a0\u30cf\u30a4\u30d3\u30b8\u30e7\u30f3\u00a0\u00a0DVD\u30c8\u30fc\u30b9\u30bf\u30fc", "\r\n\u54c1\u756a\uff1a\u00a0 \u00a0 \u00a0 \u00a0 zuko00073", "\r\n\r\n"], "text": "[ZUKO-073]\u5144\u8cb4\u306e\u5a18\u9054\u304c\u30a8\u30ed\u304f\u4ed5\u8fbc\u307e\u308c\u3066\u3066\u5b50\u4f5c\u308a", "imgf": "https://www.goldenshark.xyz/images/ZUKO-073.jpg", "href": "http://thz2.com/thread-294009-1-319.html", "dlnk": "http://thz2.com/forum.php?mod=attachment&aid=MjUzMDI0fDdkYTMwY2Y4fDE1MjM5MjMzODh8MHwyOTQwMDk%3D"}, {"jref": "http://www.javlibrary.com/en/vl_searchbyid.php?keyword=IPZ-531", "_type": "dict", "code": "IPZ-531", "name": "\u5e0c\u5d0e\u30b8\u30a7\u30b7\u30ab", "pdat": ["\r\n\u7247\u540d\uff1a\u7f8e\u4eba\u56f3\u66f8\u9928\u54e1\u306e\u6d88\u3057\u305f\u3044\u904e\u53bb \u5e0c\u5d0e\u30b8\u30a7\u30b7\u30ab", "\r\n\u5bb9\u91cf\uff1a4.36GB", "\r\n\u683c\u5f0f\uff1amkv", "\r\n\u914d\u4fe1\u958b\u59cb\u65e5\uff1a\u00a0 \u00a0 \u00a0 \u00a0 2015/02/28", "\r\n\u5546\u54c1\u767a\u58f2\u65e5\uff1a\u00a0 \u00a0 \u00a0 \u00a0 2015/03/01", "\r\n\u53ce\u9332\u6642\u9593\uff1a\u00a0 \u00a0 \u00a0 \u00a0 159\u5206 \uff08HD\u7248\uff1a159\u5206\uff09", "\r\n\u51fa\u6f14\u8005\uff1a\u00a0 \u00a0 \u00a0 \u00a0 \u5e0c\u5d0e\u30b8\u30a7\u30b7\u30ab", "\r\n\u76e3\u7763\uff1a\u00a0 \u00a0 \u00a0 \u00a0 \u30cf\u30bf\u574a", "\r\n\u30b7\u30ea\u30fc\u30ba\uff1a\u00a0 \u00a0 \u00a0 \u00a0 \u6d88\u3057\u305f\u3044\u904e\u53bb", "\r\n\u30e1\u30fc\u30ab\u30fc\uff1a\u00a0 \u00a0 \u00a0 \u00a0 \u30a2\u30a4\u30c7\u30a2\u30dd\u30b1\u30c3\u30c8", "\r\n\u30ec\u30fc\u30d9\u30eb\uff1a\u00a0 \u00a0 \u00a0 \u00a0 \u30c6\u30a3\u30c3\u30b7\u30e5", "\r\n\u30b8\u30e3\u30f3\u30eb\uff1a\u00a0 \u00a0 \u00a0 \u00a0 \u5358\u9ad4\u4f5c\u54c1\u00a0\u00a0\u5f37\u59e6\u00a0\u00a0\u304a\u59c9\u3055\u3093\u00a0\u00a0\u7f9e\u6065\u00a0\u00a0\u30a4\u30e9\u30de\u30c1\u30aa\u00a0\u00a0\u30c7\u30b8\u30e2\u00a0\u00a0\u7368\u5360\u914d\u4fe1\u00a0\u00a0\u30cf\u30a4\u30d3\u30b8\u30e7\u30f3", "\r\n\u54c1\u756a\uff1a\u00a0 \u00a0 \u00a0 \u00a0 ipz00531", "\r\n\r\n"], "text": "[IPZ-531]\u7f8e\u4eba\u56f3\u66f8\u9928\u54e1\u306e\u6d88\u3057\u305f\u3044\u904e\u53bb \u5e0c\u5d0e\u30b8\u30a7\u30b7\u30ab", "imgf": "https://www.goldenshark.xyz/images/IPZ-531.jpg", "href": "http://thz2.com/thread-289459-1-319.html", "dlnk": "http://thz2.com/forum.php?mod=attachment&aid=MjUyNjE3fDMyMzE3YzkxfDE1MjM5MjMzODl8MHwyODk0NTk%3D"}, {"jref": "http://www.javlibrary.com/en/vl_searchbyid.php?keyword=IPZ-533", "_type": "dict", "code": "IPZ-533", "name": "\u5e0c\u5cf6\u3042\u3044\u308a", "pdat": ["\r\n\u7247\u540d\uff1a\u9650\u754c\u30ae\u30ea\u30ae\u30ea\u5927\u91cf\u6f6e\u5674\u304d\u30a2\u30af\u30e1 \u6012\u6d9b\u306e160\u5206SPECIAL \u5e0c\u5cf6\u3042\u3044\u308a", "\r\n\u5bb9\u91cf\uff1a4.32Gb", "\r\n\u683c\u5f0f\uff1amkv", "\r\n\u914d\u4fe1\u958b\u59cb\u65e5\uff1a\u00a0 \u00a0 \u00a0 \u00a0 2015/02/28", "\r\n\u5546\u54c1\u767a\u58f2\u65e5\uff1a\u00a0 \u00a0 \u00a0 \u00a0 2015/03/01", "\r\n\u53ce\u9332\u6642\u9593\uff1a\u00a0 \u00a0 \u00a0 \u00a0 157\u5206 \uff08HD\u7248\uff1a157\u5206\uff09", "\r\n\u51fa\u6f14\u8005\uff1a\u00a0 \u00a0 \u00a0 \u00a0 \u5e0c\u5cf6\u3042\u3044\u308a", "\r\n\u76e3\u7763\uff1a\u00a0 \u00a0 \u00a0 \u00a0 \u6ca2\u5eb5", "\r\n\u30b7\u30ea\u30fc\u30ba\uff1a\u00a0 \u00a0 \u00a0 \u00a0 \u9650\u754c\u30ae\u30ea\u30ae\u30ea\u30a2\u30af\u30e1", "\r\n\u30e1\u30fc\u30ab\u30fc\uff1a\u00a0 \u00a0 \u00a0 \u00a0 \u30a2\u30a4\u30c7\u30a2\u30dd\u30b1\u30c3\u30c8", "\r\n\u30ec\u30fc\u30d9\u30eb\uff1a\u00a0 \u00a0 \u00a0 \u00a0 \u30c6\u30a3\u30c3\u30b7\u30e5", "\r\n\u30b8\u30e3\u30f3\u30eb\uff1a\u00a0 \u00a0 \u00a0 \u00a0 \u30cf\u30a4\u30d3\u30b8\u30e7\u30f3\u00a0\u00a0\u7368\u5360\u914d\u4fe1\u00a0\u00a0\u30c7\u30b8\u30e2\u00a0\u00a0\u8abf\u6559?\u5974\u96b7\u00a0\u00a0\u7f8e\u5c11\u5973\u00a0\u00a0\u6f6e\u5439\u304d\u00a0\u00a0\u5358\u9ad4\u4f5c\u54c1", "\r\n\u54c1\u756a\uff1a\u00a0 \u00a0 \u00a0 \u00a0 ipz00533", "\r\n\r\n"], "text": "[IPZ-533]\u5927\u91cf\u6f6e\u5674\u304d\u30a2\u30af\u30e1 \u6012\u6d9b\u306e160\u5206SPECIAL \u5e0c\u5cf6\u3042\u3044\u308a", "imgf": "https://www.goldenshark.xyz/images/IPZ-533.jpg", "href": "http://thz2.com/thread-289471-1-319.html", "dlnk": "http://thz2.com/forum.php?mod=attachment&aid=MjUyNjIxfGEwNGVkZmNhfDE1MjM5MjMzODl8MHwyODk0NzE%3D"}, {"jref": "http://www.javlibrary.com/en/vl_searchbyid.php?keyword=IPZ-530", "_type": "dict", "code": "IPZ-530", "name": "\u5929\u6d77\u3064\u3070\u3055", "pdat": ["\r\n\u7247\u540d\uff1a\u30bb\u30c3\u30af\u30b9\u30dc\u30e9\u30f3\u30c6\u30a3\u30a2 \u5929\u6d77\u3064\u3070\u3055", "\r\n\u5bb9\u91cf\uff1a4.41GB", "\r\n\u683c\u5f0f\uff1amkv", "\r\n\u914d\u4fe1\u958b\u59cb\u65e5\uff1a\u00a0 \u00a0 \u00a0 \u00a0 2015/02/28", "\r\n\u5546\u54c1\u767a\u58f2\u65e5\uff1a\u00a0 \u00a0 \u00a0 \u00a0 2015/03/01", "\r\n\u53ce\u9332\u6642\u9593\uff1a\u00a0 \u00a0 \u00a0 \u00a0 159\u5206 \uff08HD\u7248\uff1a159\u5206\uff09", "\r\n\u51fa\u6f14\u8005\uff1a\u00a0 \u00a0 \u00a0 \u00a0 \u5929\u6d77\u3064\u3070\u3055", "\r\n\u76e3\u7763\uff1a\u00a0 \u00a0 \u00a0 \u00a0 X", "\r\n\u30b7\u30ea\u30fc\u30ba\uff1a\u00a0 \u00a0 \u00a0 \u00a0 \u30bb\u30c3\u30af\u30b9\u30dc\u30e9\u30f3\u30c6\u30a3\u30a2", "\r\n\u30e1\u30fc\u30ab\u30fc\uff1a\u00a0 \u00a0 \u00a0 \u00a0 \u30a2\u30a4\u30c7\u30a2\u30dd\u30b1\u30c3\u30c8", "\r\n\u30ec\u30fc\u30d9\u30eb\uff1a\u00a0 \u00a0 \u00a0 \u00a0 \u30c6\u30a3\u30c3\u30b7\u30e5", "\r\n\u30b8\u30e3\u30f3\u30eb\uff1a\u00a0 \u00a0 \u00a0 \u00a0 \u30cf\u30a4\u30d3\u30b8\u30e7\u30f3\u00a0\u00a0\u30b3\u30b9\u30d7\u30ec\u00a0\u00a0\u6deb\u8a9e\u00a0\u00a0\u9854\u5c04\u00a0\u00a0\u4e3b\u89b3\u00a0\u00a0\u62d8\u675f\u00a0\u00a0\u5358\u9ad4\u4f5c\u54c1\u00a0\u00a0\u30c7\u30b8\u30e2\u00a0\u00a0\u7368\u5360\u914d\u4fe1", "\r\n\u54c1\u756a\uff1a\u00a0 \u00a0 \u00a0 \u00a0 ipz00530", "\r\n\r\n"], "text": "[IPZ-530]\u30bb\u30c3\u30af\u30b9\u30dc\u30e9\u30f3\u30c6\u30a3\u30a2 \u5929\u6d77\u3064\u3070\u3055", "imgf": "https://www.goldenshark.xyz/images/IPZ-530.jpg", "href": "http://thz2.com/thread-289455-1-319.html", "dlnk": "http://thz2.com/forum.php?mod=attachment&aid=MjUyNjE1fDJhNWUwNWM0fDE1MjM5MjMzOTF8MHwyODk0NTU%3D"}, {"jref": "http://www.javlibrary.com/en/vl_searchbyid.php?keyword=JUFD-452", "_type": "dict", "code": "JUFD-452", "name": "\u4f50\u85e4\u9065\u5e0c", "pdat": ["\r\n\u7247\u540d\uff1a\u7537\u6027\u793e\u54e1\u5c02\u7528\u8089\u4fbf\u5668\u30aa\u30d5\u30a3\u30b9\u30ec\u30c7\u30a3\uff5e\u6027\u6b32\u51e6\u7406\u8ab2\u306b\u914d\u5c5e\u3055\u308c\u305f\u65b0\u4eba\u5de8\u4e73\uff5e \u3055\u3068\u3046\u9065\u5e0c", "\r\n\u5bb9\u91cf\uff1a4.85Gb", "\r\n\u683c\u5f0f\uff1amkv", "\r\n\u914d\u4fe1\u958b\u59cb\u65e5\uff1a\u00a0 \u00a0 \u00a0 \u00a0 2015/02/28", "\r\n\u5546\u54c1\u767a\u58f2\u65e5\uff1a\u00a0 \u00a0 \u00a0 \u00a0 2015/03/01", "\r\n\u53ce\u9332\u6642\u9593\uff1a\u00a0 \u00a0 \u00a0 \u00a0 175\u5206 \uff08HD\u7248\uff1a175\u5206\uff09", "\r\n\u51fa\u6f14\u8005\uff1a\u00a0 \u00a0 \u00a0 \u00a0 \u3055\u3068\u3046\u9059\u5e0c", "\r\n\u76e3\u7763\uff1a\u00a0 \u00a0 \u00a0 \u00a0 TAKE-D", "\r\n\u30b7\u30ea\u30fc\u30ba\uff1a\u00a0 \u00a0 \u00a0 \u00a0 \u7537\u6027\u793e\u54e1\u5c02\u7528\u8089\u4fbf\u5668\u30aa\u30d5\u30a3\u30b9\u30ec\u30c7\u30a3", "\r\n\u30e1\u30fc\u30ab\u30fc\uff1a\u00a0 \u00a0 \u00a0 \u00a0 Fitch", "\r\n\u30ec\u30fc\u30d9\u30eb\uff1a\u00a0 \u00a0 \u00a0 \u00a0 Fitch", "\r\n\u30b8\u30e3\u30f3\u30eb\uff1a\u00a0 \u00a0 \u00a0 \u00a0 \u5de8\u4e73\u30d5\u30a7\u30c1\u00a0\u00a0\u30cf\u30a4\u30d3\u30b8\u30e7\u30f3\u00a0\u00a0\u7368\u5360\u914d\u4fe1\u00a0\u00a0\u30c7\u30b8\u30e2\u00a0\u00a0\u5358\u9ad4\u4f5c\u54c1\u00a0\u00a0\u30d1\u30a4\u30ba\u30ea\u00a0\u00a0\u6f6e\u5439\u304d\u00a0\u00a0\u8077\u696d\u8272\u3005\u00a0\u00a0\u4e2d\u51fa\u3057", "\r\n\u54c1\u756a\uff1a\u00a0 \u00a0 \u00a0 \u00a0 jufd00452", "\r\n\r\n"], "text": "[JUFD-452]\u7537\u6027\u793e\u54e1\u5c02\u7528\u8089\u4fbf\u5668", "imgf": "https://www.goldenshark.xyz/images/JUFD-452.jpg", "href": "http://thz2.com/thread-289405-1-320.html", "dlnk": "http://thz2.com/forum.php?mod=attachment&aid=MjUyNTk2fGQwM2VhMDJhfDE1MjM5MjMzOTF8MHwyODk0MDU%3D"}]