[{"jref": "http://www.javlibrary.com/en/vl_searchbyid.php?keyword=SCPX-020", "_type": "dict", "code": "SCPX-020", "name": "\u571f\u5c4b\u3042\u3055\u307f", "pdat": ["\r\n\u7247\u540d\uff1a\u5c71\u5f62\u770c\u306b\u3042\u308b\u5730\u5143\u25cf\u5b66\u751f\u304c\u624b\u4f1d\u3046\u6e29\u6cc9\u5bbf\u3067\u306f\u3001\u5973\u5c06\u306b\u5185\u7dd2\u3067\u7f8e\u5c11\u5973\u751f\u672c\u756a\u304c\u53ef\u80fd\u3068\u3044\u3046\u5642\u306f\u672c\u5f53\u306a\u306e\u304b\uff01\uff1f", "\r\n\u5bb9\u91cf\uff1a4.23GB", "\r\n\u683c\u5f0f\uff1amkv", "\r\n\u914d\u4fe1\u958b\u59cb\u65e5\uff1a\u00a0 \u00a0 \u00a0 \u00a0 2015/02/27", "\r\n\u5546\u54c1\u767a\u58f2\u65e5\uff1a\u00a0 \u00a0 \u00a0 \u00a0 2015/02/27", "\r\n\u53ce\u9332\u6642\u9593\uff1a\u00a0 \u00a0 \u00a0 \u00a0 154\u5206 \uff08HD\u7248\uff1a154\u5206\uff09", "\r\n\u51fa\u6f14\u8005\uff1a\u00a0 \u00a0 \u00a0 \u00a0 ----", "\r\n\u76e3\u7763\uff1a\u00a0 \u00a0 \u00a0 \u00a0 AKIRA", "\r\n\u30b7\u30ea\u30fc\u30ba\uff1a\u00a0 \u00a0 \u00a0 \u00a0 ----", "\r\n\u30e1\u30fc\u30ab\u30fc\uff1a\u00a0 \u00a0 \u00a0 \u00a0 \u30b9\u30af\u30fc\u30d7", "\r\n\u30ec\u30fc\u30d9\u30eb\uff1a\u00a0 \u00a0 \u00a0 \u00a0 SCOOP\uff08\u30b9\u30af\u30fc\u30d7\uff09", "\r\n\u30b8\u30e3\u30f3\u30eb\uff1a\u00a0 \u00a0 \u00a0 \u00a0 \u4e2d\u51fa\u3057\u00a0\u00a0\u30df\u30cb\u7cfb?\u5c0f\u67c4\u00a0\u00a0\u8ca7\u4e73?\u5fae\u4e73\u00a0\u00a0\u30ed\u30ea\u7cfb\u00a0\u00a0\u5973\u5b50\u6821\u751f\u00a0\u00a0\u30cf\u30a4\u30d3\u30b8\u30e7\u30f3", "\r\n\u54c1\u756a\uff1a\u00a0 \u00a0 \u00a0 \u00a0 h_565scpx00020", "\r\n\r\n"], "text": "[SCPX-020]\u5973\u5c06\u306b\u5185\u7dd2\u3067\u7f8e\u5c11\u5973\u751f\u672c\u756a\u304c\u53ef\u80fd\u3068\u3044\u3046\u5642\u306f\u672c\u5f53\u306a\u306e\u304b\uff01\uff1f", "imgf": "https://www.goldenshark.xyz/images/SCPX-020.jpg", "href": "http://thz2.com/thread-287347-1-320.html", "dlnk": "http://thz2.com/forum.php?mod=attachment&aid=MjUyMzU4fGU2NTMwNTc4fDE1MjM5MjMzOTJ8MHwyODczNDc%3D"}, {"jref": "http://www.javlibrary.com/en/vl_searchbyid.php?keyword=BBAN-032", "_type": "dict", "code": "BBAN-032", "name": "\u5ddd\u6751\u307e\u3084", "pdat": ["\r\n\u7247\u540d\uff1a\u4eca\u307e\u3067\u5473\u308f\u3063\u305f\u4e8b\u306e\u306a\u3044\u30ec\u30ba\u30c6\u30af\u3067\u5bdd\u53d6\u3089\u308c\u3066\u2026\u3002 \u611b\u9808\u5fc3\u4e9c \u5ddd\u6751\u307e\u3084", "\r\n\u5bb9\u91cf\uff1a4.07GB", "\r\n\u683c\u5f0f\uff1amkv", "\r\n\u914d\u4fe1\u958b\u59cb\u65e5\uff1a\u00a0 \u00a0 \u00a0 \u00a0 2015/03/05 10:00\uff5e", "\r\n\u5546\u54c1\u767a\u58f2\u65e5\uff1a\u00a0 \u00a0 \u00a0 \u00a0 2015/03/07", "\r\n\u53ce\u9332\u6642\u9593\uff1a\u00a0 \u00a0 \u00a0 \u00a0 148\u5206 \uff08HD\u7248\uff1a148\u5206\uff09", "\r\n\u51fa\u6f14\u8005\uff1a\u00a0 \u00a0 \u00a0 \u00a0 \u5ddd\u6751\u307e\u3084 \u611b\u9808\u5fc3\u4e9c \u7be0\u7530\u3086\u3046", "\r\n\u76e3\u7763\uff1a\u00a0 \u00a0 \u00a0 \u00a0 ----", "\r\n\u30b7\u30ea\u30fc\u30ba\uff1a\u00a0 \u00a0 \u00a0 \u00a0 ----", "\r\n\u30e1\u30fc\u30ab\u30fc\uff1a\u00a0 \u00a0 \u00a0 \u00a0 \u30d3\u30d3\u30a2\u30f3", "\r\n\u30ec\u30fc\u30d9\u30eb\uff1a\u00a0 \u00a0 \u00a0 \u00a0 \u30d3\u30d3\u30a2\u30f3", "\r\n\u30b8\u30e3\u30f3\u30eb\uff1a\u00a0 \u00a0 \u00a0 \u00a0 \u30ec\u30ba\u00a0\u00a0\u30ec\u30ba\u30ad\u30b9\u00a0\u00a0\u7f8e\u5c11\u5973\u00a0\u00a0\u5be2\u53d6\u308a?\u5be2\u53d6\u3089\u308c\u00a0\u00a0\u30af\u30f3\u30cb\u00a0\u00a0\u7368\u5360\u914d\u4fe1\u00a0\u00a0\u30cf\u30a4\u30d3\u30b8\u30e7\u30f3", "\r\n\u54c1\u756a\uff1a\u00a0 \u00a0 \u00a0 \u00a0 bban000322", "\r\n\r\n"], "text": "[BBAN-032]\u4eca\u307e\u3067\u5473\u308f\u3063\u305f\u4e8b\u306e\u306a\u3044\u30ec\u30ba\u30c6\u30af\u3067\u5bdd\u53d6\u3089\u308c\u3066\u2026\u3002 \u611b\u9808\u5fc3\u4e9c \u5ddd\u6751\u307e\u3084", "imgf": "https://www.goldenshark.xyz/images/BBAN-032.jpg", "href": "http://thz2.com/thread-289300-1-320.html", "dlnk": "http://thz2.com/forum.php?mod=attachment&aid=MjUyNTY4fDdiNDhmMjYwfDE1MjM5MjMzOTN8MHwyODkzMDA%3D"}, {"jref": "http://www.javlibrary.com/en/vl_searchbyid.php?keyword=TMCY-065", "_type": "dict", "code": "TMCY-065", "name": "\u5c0f\u5ddd\u3081\u308b\u308b", "pdat": ["\r\n\u7247\u540d\uff1a\u304a\u9152\u304f\u3055\u3044\u5927\u4eba\u3082\u30ad\u30c1\u30f3\u3068\u304a\u76f8\u624b\u3059\u308b\u305e\u3044", "\r\n\u5bb9\u91cf\uff1a3.72GB", "\r\n\u683c\u5f0f\uff1amkv", "\r\n\u914d\u4fe1\u958b\u59cb\u65e5\uff1a\u00a0 \u00a0 \u00a0 \u00a0 2015/02/27", "\r\n\u5546\u54c1\u767a\u58f2\u65e5\uff1a\u00a0 \u00a0 \u00a0 \u00a0 2015/02/27", "\r\n\u53ce\u9332\u6642\u9593\uff1a\u00a0 \u00a0 \u00a0 \u00a0 134\u5206 \uff08HD\u7248\uff1a134\u5206\uff09", "\r\n\u51fa\u6f14\u8005\uff1a\u00a0 \u00a0 \u00a0 \u00a0 \u5c0f\u5ddd\u3081\u308b\u308b", "\r\n\u76e3\u7763\uff1a\u00a0 \u00a0 \u00a0 \u00a0 ----", "\r\n\u30b7\u30ea\u30fc\u30ba\uff1a\u00a0 \u00a0 \u00a0 \u00a0 ----", "\r\n\u30e1\u30fc\u30ab\u30fc\uff1a\u00a0 \u00a0 \u00a0 \u00a0 \u30d0\u30eb\u30bf\u30f3", "\r\n\u30ec\u30fc\u30d9\u30eb\uff1a\u00a0 \u00a0 \u00a0 \u00a0 BALTAN Candy", "\r\n\u30b8\u30e3\u30f3\u30eb\uff1a\u00a0 \u00a0 \u00a0 \u00a0 \u30cf\u30a4\u30d3\u30b8\u30e7\u30f3\u00a0\u00a0\u5358\u9ad4\u4f5c\u54c1\u00a0\u00a0\u30cb\u30fc\u30bd\u30c3\u30af\u30b9\u00a0\u00a0\u5de8\u4e73\u00a0\u00a0\u7f8e\u5c11\u5973\u00a0\u00a0\u30ed\u30ea\u7cfb", "\r\n\u54c1\u756a\uff1a\u00a0 \u00a0 \u00a0 \u00a0 h_452tmcy00065", "\r\n\r\n"], "text": "[TMCY-065]\u304a\u9152\u304f\u3055\u3044\u5927\u4eba\u3082\u30ad\u30c1\u30f3\u3068\u304a\u76f8\u624b\u3059\u308b\u305e\u3044", "imgf": "https://www.goldenshark.xyz/images/TMCY-065.jpg", "href": "http://thz2.com/thread-287264-1-320.html", "dlnk": "http://thz2.com/forum.php?mod=attachment&aid=MjUyMzMwfGU0MTVlMzY0fDE1MjM5MjMzOTN8MHwyODcyNjQ%3D"}, {"jref": "http://www.javlibrary.com/en/vl_searchbyid.php?keyword=TMDI-055", "_type": "dict", "code": "TMDI-055", "name": "\u6709\u672c\u7d17\u4e16", "pdat": ["\r\n\u7247\u540d\uff1a\u5352\u696d\u4ee5\u6765\u306e\u5f7c\u5973\u306f\u5de6\u624b\u85ac\u6307\u4ee5\u5916\u5909\u308f\u3089\u306c\u59ff", "\r\n\u5bb9\u91cf\uff1a3.64gb", "\r\n\u683c\u5f0f\uff1amkv", "\r\n\u914d\u4fe1\u958b\u59cb\u65e5\uff1a\u00a0 \u00a0 \u00a0 \u00a0 2015/02/27", "\r\n\u5546\u54c1\u767a\u58f2\u65e5\uff1a\u00a0 \u00a0 \u00a0 \u00a0 2015/02/27", "\r\n\u53ce\u9332\u6642\u9593\uff1a\u00a0 \u00a0 \u00a0 \u00a0 131\u5206 \uff08HD\u7248\uff1a131\u5206\uff09", "\r\n\u51fa\u6f14\u8005\uff1a\u00a0 \u00a0 \u00a0 \u00a0 \u6709\u672c\u7d17\u4e16", "\r\n\u76e3\u7763\uff1a\u00a0 \u00a0 \u00a0 \u00a0 ----", "\r\n\u30b7\u30ea\u30fc\u30ba\uff1a\u00a0 \u00a0 \u00a0 \u00a0 ----", "\r\n\u30e1\u30fc\u30ab\u30fc\uff1a\u00a0 \u00a0 \u00a0 \u00a0 \u30d0\u30eb\u30bf\u30f3", "\r\n\u30ec\u30fc\u30d9\u30eb\uff1a\u00a0 \u00a0 \u00a0 \u00a0 BALTAN Diamond", "\r\n\u30b8\u30e3\u30f3\u30eb\uff1a\u00a0 \u00a0 \u00a0 \u00a0 \u30cf\u30a4\u30d3\u30b8\u30e7\u30f3\u00a0\u00a0\u5358\u9ad4\u4f5c\u54c1\u00a0\u00a0\u30d1\u30a4\u30d1\u30f3\u00a0\u00a0\u4eba\u59bb\u00a0\u00a0\u30ed\u30ea\u7cfb", "\r\n\u54c1\u756a\uff1a\u00a0 \u00a0 \u00a0 \u00a0 h_452tmdi00055", "\r\n\r\n"], "text": "[TMDI-055]\u5352\u696d\u4ee5\u6765\u306e\u5f7c\u5973\u306f\u5de6\u624b\u85ac\u6307\u4ee5\u5916\u5909\u308f\u3089\u306c\u59ff", "imgf": "https://www.goldenshark.xyz/images/TMDI-055.jpg", "href": "http://thz2.com/thread-287297-1-320.html", "dlnk": "http://thz2.com/forum.php?mod=attachment&aid=MjUyMzM0fGIxZWIxYWEzfDE1MjM5MjMzOTR8MHwyODcyOTc%3D"}, {"jref": "http://www.javlibrary.com/en/vl_searchbyid.php?keyword=SCOP-280", "_type": "dict", "code": "SCOP-280", "name": "\u521d\u7f8e\u6c99\u5e0c", "pdat": ["\r\n\u7247\u540d\uff1a\u5a18\u306eSEX\u3092\u898b\u3066\u75bc\u3044\u305f\u82e5\u59bb\u306f\u3069\u3093\u306a\u7537\u306e\u7cbe\u5b50\u3082\u4e2d\u3067\u53d7\u3051\u6b62\u3081\u308b\uff01\uff1f 4", "\r\n\u5bb9\u91cf\uff1a6.62GB", "\r\n\u683c\u5f0f\uff1amkv", "\r\n\u914d\u4fe1\u958b\u59cb\u65e5\uff1a\u00a0 \u00a0 \u00a0 \u00a0 2015/02/27", "\r\n\u5546\u54c1\u767a\u58f2\u65e5\uff1a\u00a0 \u00a0 \u00a0 \u00a0 2015/02/27", "\r\n\u53ce\u9332\u6642\u9593\uff1a\u00a0 \u00a0 \u00a0 \u00a0 241\u5206 \uff08HD\u7248\uff1a241\u5206\uff09", "\r\n\u51fa\u6f14\u8005\uff1a\u00a0 \u00a0 \u00a0 \u00a0 ----", "\r\n\u76e3\u7763\uff1a\u00a0 \u00a0 \u00a0 \u00a0 K\u592a\u90ce", "\r\n\u30b7\u30ea\u30fc\u30ba\uff1a\u00a0 \u00a0 \u00a0 \u00a0 \u5a18\u306eSEX\u3092\u898b\u3066\u75bc\u3044\u305f\u82e5\u59bb\u306f\u3069\u3093\u306a\u7537\u306e\u7cbe\u5b50\u3082\u4e2d\u3067\u53d7\u3051\u6b62\u3081\u308b\uff01\uff1f", "\r\n\u30e1\u30fc\u30ab\u30fc\uff1a\u00a0 \u00a0 \u00a0 \u00a0 \u30b9\u30af\u30fc\u30d7", "\r\n\u30ec\u30fc\u30d9\u30eb\uff1a\u00a0 \u00a0 \u00a0 \u00a0 SCOOP\uff08\u30b9\u30af\u30fc\u30d7\uff09", "\r\n\u30b8\u30e3\u30f3\u30eb\uff1a\u00a0 \u00a0 \u00a0 \u00a0 \u82b1\u5ac1?\u82e5\u59bb\u00a0\u00a0\u4eba\u59bb\u00a0\u00a04\u6642\u9593\u4ee5\u4e0a\u4f5c\u54c1\u00a0\u00a0\u4f01\u756b\u00a0\u00a0\u4e2d\u51fa\u3057\u00a0\u00a0\u7d20\u4eba\u00a0\u00a0\u30cf\u30a4\u30d3\u30b8\u30e7\u30f3", "\r\n\u54c1\u756a\uff1a\u00a0 \u00a0 \u00a0 \u00a0 h_565scop00280", "\r\n\r\n"], "text": "[SCOP-280]\u5a18\u306eSEX\u3092\u898b\u3066\u75bc\u3044\u305f\u82e5\u59bb\u306f\u3069\u3093\u306a\u7537\u306e\u7cbe\u5b50\u3082\u4e2d\u3067\u53d7\u3051\u6b62\u3081\u308b\uff01\uff1f 4", "imgf": "https://www.goldenshark.xyz/images/SCOP-280.jpg", "href": "http://thz2.com/thread-287314-1-320.html", "dlnk": "http://thz2.com/forum.php?mod=attachment&aid=MjUyMzQ0fGQxZDU5OGRlfDE1MjM5MjMzOTR8MHwyODczMTQ%3D"}, {"jref": "http://www.javlibrary.com/en/vl_searchbyid.php?keyword=SCOP-284", "_type": "dict", "code": "SCOP-284", "name": "\u4f50\u85e4\u9065\u5e0c", "pdat": ["\r\n\u7247\u540d\uff1a\u672c\u756a\u3042\u308a\u306e\u88cf\u98a8\u4fd7\u3067\u3001\u30d0\u30c3\u30af\u3067\u3064\u3044\u3066\u3044\u308b\u6642\u306b\u3053\u3063\u305d\u308a\u30b4\u30e0\u3092\u5916\u3057\u3001\u305d\u306e\u307e\u307e\u30c9\u30c3\u30d7\u30ea\u751f\u4e2d\u51fa\u3057\u3057\u3061\u3083\u3044\u307e\u3057\u305f\uff01 7", "\r\n\u5bb9\u91cf\uff1a6.59Gb", "\r\n\u683c\u5f0f\uff1amkv", "\r\n\u914d\u4fe1\u958b\u59cb\u65e5\uff1a\u00a0 \u00a0 \u00a0 \u00a0 2015/02/27", "\r\n\u5546\u54c1\u767a\u58f2\u65e5\uff1a\u00a0 \u00a0 \u00a0 \u00a0 2015/02/27", "\r\n\u53ce\u9332\u6642\u9593\uff1a\u00a0 \u00a0 \u00a0 \u00a0 239\u5206 \uff08HD\u7248\uff1a239\u5206\uff09", "\r\n\u51fa\u6f14\u8005\uff1a\u00a0 \u00a0 \u00a0 \u00a0 ----", "\r\n\u76e3\u7763\uff1a\u00a0 \u00a0 \u00a0 \u00a0 \u6469\u5929\u6a13", "\r\n\u30b7\u30ea\u30fc\u30ba\uff1a\u00a0 \u00a0 \u00a0 \u00a0 \u672c\u756a\u3042\u308a\u306e\u88cf\u98a8\u4fd7\u3067\u3001\u30d0\u30c3\u30af\u3067\u3064\u3044\u3066\u3044\u308b\u6642\u306b\u3053\u3063\u305d\u308a\u30b4\u30e0\u3092\u5916\u3057", "\r\n\u30e1\u30fc\u30ab\u30fc\uff1a\u00a0 \u00a0 \u00a0 \u00a0 \u30b9\u30af\u30fc\u30d7", "\r\n\u30ec\u30fc\u30d9\u30eb\uff1a\u00a0 \u00a0 \u00a0 \u00a0 SCOOP\uff08\u30b9\u30af\u30fc\u30d7\uff09", "\r\n\u30b8\u30e3\u30f3\u30eb\uff1a\u00a0 \u00a0 \u00a0 \u00a0 \u30ad\u30e3\u30d0\u5b22?\u98a8\u4fd7\u5b22\u00a0\u00a0\u4eba\u59bb\u00a0\u00a04\u6642\u9593\u4ee5\u4e0a\u4f5c\u54c1\u00a0\u00a0\u4f01\u756b\u00a0\u00a0\u4e2d\u51fa\u3057\u00a0\u00a0\u7d20\u4eba\u00a0\u00a0\u30cf\u30a4\u30d3\u30b8\u30e7\u30f3", "\r\n\u54c1\u756a\uff1a\u00a0 \u00a0 \u00a0 \u00a0 h_565scop00284", "\r\n\r\n"], "text": "[SCOP-284]\u305d\u306e\u307e\u307e\u30c9\u30c3\u30d7\u30ea\u751f\u4e2d\u51fa\u3057\u3057\u3061\u3083\u3044\u307e\u3057\u305f\uff01 7", "imgf": "https://www.goldenshark.xyz/images/SCOP-284.jpg", "href": "http://thz2.com/thread-287327-1-320.html", "dlnk": "http://thz2.com/forum.php?mod=attachment&aid=MjUyMzUyfGZjOGI5MzMwfDE1MjM5MjMzOTZ8MHwyODczMjc%3D"}, {"jref": "http://www.javlibrary.com/en/vl_searchbyid.php?keyword=SCOP-281", "_type": "dict", "code": "SCOP-281", "name": "\u4f73\u82d7\u308b\u304b", "pdat": ["\r\n\u7247\u540d\uff1a\u76ee\u304c\u3042\u3063\u305f\u3089\u5373\u30cf\u30e1\u30ec\u30a4\u30d7\uff01\uff01\u7372\u7269\u3092\u7269\u8272\u3057\u3001\u3070\u308c\u306a\u3044\u3088\u3046\u306b\u80cc\u5f8c\u304b\u3089\u8fd1\u5bc4\u308a\u3001\u4e00\u6c17\u306b\u30cf\u30e1\u308b\uff01\uff01\u4f55\u6c17\u306a\u3044\u65e5\u5e38\u306b\u7a81\u5982\u8972\u3044\u639b\u304b\u308b\u6050\u6016", "\r\n\u5bb9\u91cf\uff1a6.68gb", "\r\n\u683c\u5f0f\uff1amkv", "\r\n\u914d\u4fe1\u958b\u59cb\u65e5\uff1a\u00a0 \u00a0 \u00a0 \u00a0 2015/02/27", "\r\n\u5546\u54c1\u767a\u58f2\u65e5\uff1a\u00a0 \u00a0 \u00a0 \u00a0 2015/02/27", "\r\n\u53ce\u9332\u6642\u9593\uff1a\u00a0 \u00a0 \u00a0 \u00a0 240\u5206 \uff08HD\u7248\uff1a240\u5206\uff09", "\r\n\u51fa\u6f14\u8005\uff1a\u00a0 \u00a0 \u00a0 \u00a0 ----", "\r\n\u76e3\u7763\uff1a\u00a0 \u00a0 \u00a0 \u00a0 U-TA", "\r\n\u30b7\u30ea\u30fc\u30ba\uff1a\u00a0 \u00a0 \u00a0 \u00a0 ----", "\r\n\u30e1\u30fc\u30ab\u30fc\uff1a\u00a0 \u00a0 \u00a0 \u00a0 \u30b9\u30af\u30fc\u30d7", "\r\n\u30ec\u30fc\u30d9\u30eb\uff1a\u00a0 \u00a0 \u00a0 \u00a0 SCOOP\uff08\u30b9\u30af\u30fc\u30d7\uff09", "\r\n\u30b8\u30e3\u30f3\u30eb\uff1a\u00a0 \u00a0 \u00a0 \u00a0 \u5373\u30cf\u30e1\u00a0\u00a04\u6642\u9593\u4ee5\u4e0a\u4f5c\u54c1\u00a0\u00a0\u5de8\u4e73\u00a0\u00a0\u5f37\u59e6\u00a0\u00a0\u4e2d\u51fa\u3057\u00a0\u00a0\u7d20\u4eba\u00a0\u00a0\u30cf\u30a4\u30d3\u30b8\u30e7\u30f3", "\r\n\u54c1\u756a\uff1a\u00a0 \u00a0 \u00a0 \u00a0 h_565scop00281", "\r\n\r\n"], "text": "[SCOP-281]\u4f55\u6c17\u306a\u3044\u65e5\u5e38\u306b\u7a81\u5982\u8972\u3044\u639b\u304b\u308b\u6050\u6016", "imgf": "https://www.goldenshark.xyz/images/SCOP-281.jpg", "href": "http://thz2.com/thread-287316-1-320.html", "dlnk": "http://thz2.com/forum.php?mod=attachment&aid=MjUyMzQ2fDlhNjRlY2QyfDE1MjM5MjMzOTV8MHwyODczMTY%3D"}, {"jref": "http://www.javlibrary.com/en/vl_searchbyid.php?keyword=VEMA-096", "_type": "dict", "code": "VEMA-096", "name": "\u6ce2\u591a\u91ce\u7ed3\u8863", "pdat": ["\r\n\u7247\u540d\uff1a\u53cb\u4eba\u306e\u59bb\u306f\u30c9\u30b9\u30b1\u30d9\u5bb6\u5ead\u6559\u5e2b \u6ce2\u591a\u91ce\u7d50\u8863", "\r\n\u5bb9\u91cf\uff1a2.69GB", "\r\n\u683c\u5f0f\uff1amkv", "\r\n\u914d\u4fe1\u958b\u59cb\u65e5\uff1a\u00a0 \u00a0 \u00a0 \u00a0 2015/03/06 10:00\uff5e", "\r\n\u5546\u54c1\u767a\u58f2\u65e5\uff1a\u00a0 \u00a0 \u00a0 \u00a0 2015/03/07", "\r\n\u53ce\u9332\u6642\u9593\uff1a\u00a0 \u00a0 \u00a0 \u00a0 97\u5206 \uff08HD\u7248\uff1a97\u5206\uff09", "\r\n\u51fa\u6f14\u8005\uff1a\u00a0 \u00a0 \u00a0 \u00a0 \u6ce2\u591a\u91ce\u7d50\u8863", "\r\n\u76e3\u7763\uff1a\u00a0 \u00a0 \u00a0 \u00a0 \u7389\u585a\u3073\u3093\u3054", "\r\n\u30b7\u30ea\u30fc\u30ba\uff1a\u00a0 \u00a0 \u00a0 \u00a0 \u53cb\u4eba\u306e\u59bb\u306f\u30c9\u30b9\u30b1\u30d9\u5bb6\u5ead\u6559\u5e2b", "\r\n\u30e1\u30fc\u30ab\u30fc\uff1a\u00a0 \u00a0 \u00a0 \u00a0 VENUS", "\r\n\u30ec\u30fc\u30d9\u30eb\uff1a\u00a0 \u00a0 \u00a0 \u00a0 \u5973\u795e\uff08\u30f4\u30a3\u30fc\u30ca\u30b9\uff09", "\r\n\u30b8\u30e3\u30f3\u30eb\uff1a\u00a0 \u00a0 \u00a0 \u00a0 \u30cf\u30a4\u30d3\u30b8\u30e7\u30f3\u00a0\u00a0\u7368\u5360\u914d\u4fe1\u00a0\u00a0\u719f\u5973\u00a0\u00a0\u4eba\u59bb\u00a0\u00a0\u5bb6\u5ead\u6559\u5e2b\u00a0\u00a0\u5358\u9ad4\u4f5c\u54c1\u00a0\u00a0\u4e2d\u51fa\u3057", "\r\n\u54c1\u756a\uff1a\u00a0 \u00a0 \u00a0 \u00a0 vema00096", "\r\n\r\n"], "text": "[VEMA-096]\u53cb\u4eba\u306e\u59bb\u306f\u30c9\u30b9\u30b1\u30d9\u5bb6\u5ead\u6559\u5e2b \u6ce2\u591a\u91ce\u7d50\u8863", "imgf": "https://www.goldenshark.xyz/images/VEMA-096.jpg", "href": "http://thz2.com/thread-287221-1-320.html", "dlnk": "http://thz2.com/forum.php?mod=attachment&aid=MjUyMzEwfDhmNDZkZWFmfDE1MjM5MjMzOTZ8MHwyODcyMjE%3D"}, {"jref": "http://www.javlibrary.com/en/vl_searchbyid.php?keyword=MUM-152", "_type": "dict", "code": "MUM-152", "name": "\u306a\u3054\u307f", "pdat": ["\r\n\u7247\u540d\uff1a\u751f\u307e\u308c\u3066\u521d\u3081\u3066\u306e\u304a\u3057\u308a\u3002\u30a2\u30ca\u30eb\u306f\u3082\u3046\u4e00\u3064\u306e\u30de\u25cb\u30b3\u3060\u3068\u6559\u3048\u3089\u308c\u308b\u3002\u306a\u3054\u307f", "\r\n\u5bb9\u91cf\uff1a5.53Gb", "\r\n\u683c\u5f0f\uff1amkv", "\r\n\u914d\u4fe1\u958b\u59cb\u65e5\uff1a\u00a0 \u00a0 \u00a0 \u00a0 2015/02/28 10:00\uff5e", "\r\n\u5546\u54c1\u767a\u58f2\u65e5\uff1a\u00a0 \u00a0 \u00a0 \u00a0 2015/03/01", "\r\n\u53ce\u9332\u6642\u9593\uff1a\u00a0 \u00a0 \u00a0 \u00a0 200\u5206 \uff08HD\u7248\uff1a200\u5206\uff09", "\r\n\u51fa\u6f14\u8005\uff1a\u00a0 \u00a0 \u00a0 \u00a0 \u306a\u3054\u307f", "\r\n\u76e3\u7763\uff1a\u00a0 \u00a0 \u00a0 \u00a0 \u30d4\u30a8\u30ed\u7530", "\r\n\u30b7\u30ea\u30fc\u30ba\uff1a\u00a0 \u00a0 \u00a0 \u00a0 \u30a2\u30ca\u30eb\u306f\u3082\u3046\u4e00\u3064\u306e\u30de\u30f3\u30b3\u3060\u3068\u6559\u3048\u3089\u308c\u308b\u3002", "\r\n\u30e1\u30fc\u30ab\u30fc\uff1a\u00a0 \u00a0 \u00a0 \u00a0 \u30df\u30cb\u30de\u30e0", "\r\n\u30ec\u30fc\u30d9\u30eb\uff1a\u00a0 \u00a0 \u00a0 \u00a0 \u30df\u30cb\u30de\u30e0", "\r\n\u30b8\u30e3\u30f3\u30eb\uff1a\u00a0 \u00a0 \u00a0 \u00a0 \u30a2\u30ca\u30eb\u00a0\u00a0\u8ca7\u4e73?\u5fae\u4e73\u00a0\u00a0\u30df\u30cb\u7cfb?\u5c0f\u67c4\u00a0\u00a0\u30ed\u30ea\u7cfb\u00a0\u00a0\u30a4\u30bf\u30ba\u30e9\u00a0\u00a0\u5358\u9ad4\u4f5c\u54c1\u00a0\u00a0\u7368\u5360\u914d\u4fe1\u00a0\u00a0\u30cf\u30a4\u30d3\u30b8\u30e7\u30f3", "\r\n\u54c1\u756a\uff1a\u00a0 \u00a0 \u00a0 \u00a0 mum00152", "\r\n\r\n"], "text": "[MUM-152]\u30a2\u30ca\u30eb\u306f\u3082\u3046\u4e00\u3064\u306e\u30de\u25cb\u30b3\u3060\u3068\u6559\u3048\u3089\u308c\u308b\u3002\u306a\u3054\u307f", "imgf": "https://www.goldenshark.xyz/images/MUM-152.jpg", "href": "http://thz2.com/thread-287229-1-320.html", "dlnk": "http://thz2.com/forum.php?mod=attachment&aid=MjUyMzE4fDI4NmY0MWM1fDE1MjM5MjMzOTd8MHwyODcyMjk%3D"}, {"jref": "http://www.javlibrary.com/en/vl_searchbyid.php?keyword=OKAD-512", "_type": "dict", "code": "OKAD-512", "name": "\u521d\u7f8e\u6c99\u5e0c", "pdat": ["\r\n\u7247\u540d\uff1a\u7f8e\u4eba4\u59c9\u59b9\u3068\u30cf\u30fc\u30ec\u30e0\u540c\u68f2\u751f\u6d3b \u521d\u7f8e\u6c99\u5e0c \u4e59\u8449\u306a\u306a\u305b \u963f\u90e8\u4e43\u307f\u304f \u611b\u9808\u5fc3\u4e9c", "\r\n\u5bb9\u91cf\uff1a4.03GB", "\r\n\u683c\u5f0f\uff1amkv", "\r\n\u914d\u4fe1\u958b\u59cb\u65e5\uff1a\u00a0 \u00a0 \u00a0 \u00a0 2015/02/27", "\r\n\u5546\u54c1\u767a\u58f2\u65e5\uff1a\u00a0 \u00a0 \u00a0 \u00a0 2015/02/27", "\r\n\u53ce\u9332\u6642\u9593\uff1a\u00a0 \u00a0 \u00a0 \u00a0 145\u5206 \uff08HD\u7248\uff1a145\u5206\uff09", "\r\n\u51fa\u6f14\u8005\uff1a\u00a0 \u00a0 \u00a0 \u00a0 \u521d\u7f8e\u6c99\u5e0c \u4e59\u8449\u306a\u306a\u305b \u963f\u90e8\u4e43\u307f\u304f \u611b\u9808\u5fc3\u4e9c", "\r\n\u76e3\u7763\uff1a\u00a0 \u00a0 \u00a0 \u00a0 \u6469\u5929\u6a13", "\r\n\u30b7\u30ea\u30fc\u30ba\uff1a\u00a0 \u00a0 \u00a0 \u00a0 ----", "\r\n\u30e1\u30fc\u30ab\u30fc\uff1a\u00a0 \u00a0 \u00a0 \u00a0 \u30b1\u30a4?\u30a8\u30e0?\u30d7\u30ed\u30c7\u30e5\u30fc\u30b9", "\r\n\u30ec\u30fc\u30d9\u30eb\uff1a\u00a0 \u00a0 \u00a0 \u00a0 \u304a\u304b\u305a\u3002", "\r\n\u30b8\u30e3\u30f3\u30eb\uff1a\u00a0 \u00a0 \u00a0 \u00a0 \u30ed\u30ea\u7cfb\u00a0\u00a0\u7f8e\u5c11\u5973\u00a0\u00a0\u4f01\u756b\u00a0\u00a0\u4e2d\u51fa\u3057\u00a0\u00a0\u30cf\u30a4\u30d3\u30b8\u30e7\u30f3", "\r\n\u54c1\u756a\uff1a\u00a0 \u00a0 \u00a0 \u00a0 84okad00512", "\r\n\r\n"], "text": "[OKAD-512]\u7f8e\u4eba4\u59c9\u59b9\u3068\u30cf\u30fc\u30ec\u30e0\u540c\u68f2\u751f\u6d3b \u521d\u7f8e\u6c99\u5e0c \u4e59\u8449\u306a\u306a\u305b \u963f\u90e8\u4e43\u307f\u304f \u611b\u9808\u5fc3\u4e9c", "imgf": "https://www.goldenshark.xyz/images/OKAD-512.jpg", "href": "http://thz2.com/thread-287252-1-320.html", "dlnk": "http://thz2.com/forum.php?mod=attachment&aid=MjUyMzI0fGNmOTM3NWFmfDE1MjM5MjMzOTh8MHwyODcyNTI%3D"}, {"jref": "http://www.javlibrary.com/en/vl_searchbyid.php?keyword=BTC-03", "_type": "dict", "code": "BTC-03", "name": "\u4f50\u85e4\u9065\u5e0c", "pdat": ["\r\n\u7247\u540d\uff1a\u9ed2\u4eba\u30c6\u30e9\u30c1\u25cb\u30dd\u30fb\u30aa\u30f3\u30fb\u30b6\u30fb\u30ed\u30fc\u30c9 \u3055\u3068\u3046\u9065\u5e0c\u7de8", "\r\n\u5bb9\u91cf\uff1a3.46Gb", "\r\n\u683c\u5f0f\uff1amkv", "\r\n\u767a\u58f2\u65e5\uff1a\u00a0 \u00a0 \u00a0 \u00a0 2015/02/25", "\r\n\u53ce\u9332\u6642\u9593\uff1a\u00a0 \u00a0 \u00a0 \u00a0 120\u5206", "\r\n\u51fa\u6f14\u8005\uff1a\u00a0 \u00a0 \u00a0 \u00a0 \u3055\u3068\u3046\u9059\u5e0c", "\r\n\u76e3\u7763\uff1a\u00a0 \u00a0 \u00a0 \u00a0 \u3042\u3070\u3057\u308a\u4e00\u5bb6", "\r\n\u30b7\u30ea\u30fc\u30ba\uff1a\u00a0 \u00a0 \u00a0 \u00a0 \u9ed2\u4eba\u5de8\u5927\u30de\u30e9 \u9ed2\u4eba\u30c6\u30e9\u30c1\u25cb\u30dd?\u30aa\u30f3?\u30b6?\u30ed\u30fc\u30c9", "\r\n\u30e1\u30fc\u30ab\u30fc\uff1a\u00a0 \u00a0 \u00a0 \u00a0 \u30b0\u30ed\u30fc\u30d0\u30eb\u30e1\u30c7\u30a3\u30a2\u30a8\u30f3\u30bf\u30c6\u30a4\u30f3\u30e1\u30f3\u30c8", "\r\n\u30ec\u30fc\u30d9\u30eb\uff1a\u00a0 \u00a0 \u00a0 \u00a0 \u30d6\u30e9\u30c3\u30af\u30c6\u30e9", "\r\n\u30b8\u30e3\u30f3\u30eb\uff1a\u00a0 \u00a0 \u00a0 \u00a0 \u7f8e\u4e73 \u719f\u5973 \u9ed2\u4eba\u7537\u512a \u5358\u9ad4\u4f5c\u54c1 \u4e2d\u51fa\u3057 \u9854\u5c04 \u30b5\u30f3\u30d7\u30eb\u52d5\u756b", "\r\n\u54c1\u756a\uff1a\u00a0 \u00a0 \u00a0 \u00a0 143btc03", "\r\n\r\n"], "text": "[BTC-03]\u9ed2\u4eba\u30c6\u30e9\u30c1\u25cb\u30dd\u30fb\u30aa\u30f3\u30fb\u30b6\u30fb\u30ed\u30fc\u30c9 \u3055\u3068\u3046\u9065\u5e0c\u7de8", "imgf": "https://www.goldenshark.xyz/images/BTC-03.jpg", "href": "http://thz2.com/thread-287195-1-321.html", "dlnk": "http://thz2.com/forum.php?mod=attachment&aid=MjUyMjkwfDlhMmIxNzhifDE1MjM5MjM0MDB8MHwyODcxOTU%3D"}, {"jref": "http://www.javlibrary.com/en/vl_searchbyid.php?keyword=MDTM-012", "_type": "dict", "code": "MDTM-012", "name": "\u4f73\u82d7\u308b\u304b", "pdat": ["\r\n\u7247\u540d\uff1a\u653e\u8ab2\u5f8c\u7f8e\u5c11\u5973\u56de\u6625\u30ea\u30d5\u30ec\u30af\u30bd\u30ed\u30b8\u30fc \u308b\u304b", "\r\n\u5bb9\u91cf\uff1a3.14Gb", "\r\n\u683c\u5f0f\uff1amkv", "\r\n\u914d\u4fe1\u958b\u59cb\u65e5\uff1a\u00a0 \u00a0 \u00a0 \u00a0 2015/02/27", "\r\n\u5546\u54c1\u767a\u58f2\u65e5\uff1a\u00a0 \u00a0 \u00a0 \u00a0 2015/02/27", "\r\n\u53ce\u9332\u6642\u9593\uff1a\u00a0 \u00a0 \u00a0 \u00a0 113\u5206 \uff08HD\u7248\uff1a113\u5206\uff09", "\r\n\u51fa\u6f14\u8005\uff1a\u00a0 \u00a0 \u00a0 \u00a0 \u4f73\u82d7\u308b\u304b", "\r\n\u76e3\u7763\uff1a\u00a0 \u00a0 \u00a0 \u00a0 ----", "\r\n\u30b7\u30ea\u30fc\u30ba\uff1a\u00a0 \u00a0 \u00a0 \u00a0 \u653e\u8ab2\u5f8c\u7f8e\u5c11\u5973\u56de\u6625\u30ea\u30d5\u30ec\u30af\u30bd\u30ed\u30b8\u30fc", "\r\n\u30e1\u30fc\u30ab\u30fc\uff1a\u00a0 \u00a0 \u00a0 \u00a0 \u30e1\u30c7\u30a3\u30a2\u30b9\u30c6\u30fc\u30b7\u30e7\u30f3", "\r\n\u30ec\u30fc\u30d9\u30eb\uff1a\u00a0 \u00a0 \u00a0 \u00a0 \u5b87\u5b99\u4f01\u756b", "\r\n\u30b8\u30e3\u30f3\u30eb\uff1a\u00a0 \u00a0 \u00a0 \u00a0 \u5358\u9ad4\u4f5c\u54c1\u00a0\u00a0\u9ad4\u64cd\u8457?\u30d6\u30eb\u30de\u00a0\u00a0\u30a8\u30b9\u30c6\u00a0\u00a0\u7d20\u4eba\u00a0\u00a0\u30de\u30c3\u30b5\u30fc\u30b8\u00a0\u00a0\u30cf\u30a4\u30d3\u30b8\u30e7\u30f3", "\r\n\u54c1\u756a\uff1a\u00a0 \u00a0 \u00a0 \u00a0 61mdtm00012", "\r\n\r\n"], "text": "[MDTM-012]\u653e\u8ab2\u5f8c\u7f8e\u5c11\u5973\u56de\u6625\u30ea\u30d5\u30ec\u30af\u30bd\u30ed\u30b8\u30fc \u308b\u304b", "imgf": "https://www.goldenshark.xyz/images/MDTM-012.jpg", "href": "http://thz2.com/thread-287212-1-321.html", "dlnk": "http://thz2.com/forum.php?mod=attachment&aid=MjUyMjk4fDEzMzJiZTY5fDE1MjM5MjM0MDB8MHwyODcyMTI%3D"}, {"jref": "http://www.javlibrary.com/en/vl_searchbyid.php?keyword=DXMG-027", "_type": "dict", "code": "DXMG-027", "name": "\u6ce2\u591a\u91ce\u7ed3\u8863", "pdat": ["\r\n\u7247\u540d\uff1a\u5973\u306e\u60e8\u3059\u304e\u308b\u77ac\u9593 \u9ebb\u85ac\u635c\u67fb\u5b98\u62f7\u554f \u5973\u635c\u67fb\u5b98 FILE 27 \u6ce2\u591a\u91ce\u7d50\u8863\u306e\u5834\u5408", "\r\n\u5bb9\u91cf\uff1a3.81GB", "\r\n\u683c\u5f0f\uff1amkv", "\r\n\u914d\u4fe1\u958b\u59cb\u65e5\uff1a\u00a0 \u00a0 \u00a0 \u00a0 2015/02/22", "\r\n\u5546\u54c1\u767a\u58f2\u65e5\uff1a\u00a0 \u00a0 \u00a0 \u00a0 2015/02/25", "\r\n\u53ce\u9332\u6642\u9593\uff1a\u00a0 \u00a0 \u00a0 \u00a0 137\u5206 \uff08HD\u7248\uff1a137\u5206\uff09", "\r\n\u51fa\u6f14\u8005\uff1a\u00a0 \u00a0 \u00a0 \u00a0 \u6ce2\u591a\u91ce\u7d50\u8863", "\r\n\u76e3\u7763\uff1a\u00a0 \u00a0 \u00a0 \u00a0 \u3070\u3070\u2605\u30b6\u2605\u3070\u3073\u3043", "\r\n\u30b7\u30ea\u30fc\u30ba\uff1a\u00a0 \u00a0 \u00a0 \u00a0 \u9ebb\u85ac\u635c\u67fb\u5b98\u62f7\u554f", "\r\n\u30e1\u30fc\u30ab\u30fc\uff1a\u00a0 \u00a0 \u00a0 \u00a0 BabyEntertainment", "\r\n\u30ec\u30fc\u30d9\u30eb\uff1a\u00a0 \u00a0 \u00a0 \u00a0 BLACK BABY", "\r\n\u30b8\u30e3\u30f3\u30eb\uff1a\u00a0 \u00a0 \u00a0 \u00a0 \u30cf\u30a4\u30d3\u30b8\u30e7\u30f3\u00a0\u00a0\u7368\u5360\u914d\u4fe1\u00a0\u00a0\u5358\u9ad4\u4f5c\u54c1\u00a0\u00a0\u8abf\u6559?\u5974\u96b7\u00a0\u00a0\u96fb\u30de\u00a0\u00a0\u5973\u635c\u67fb\u5b98\u00a0\u00a0\u30ae\u30ea\u30e2\u30b6\u00a0\u00a0\u8fb1\u3081", "\r\n\u54c1\u756a\uff1a\u00a0 \u00a0 \u00a0 \u00a0 dxmg00027", "\r\n\r\n"], "text": "[DXMG-027]\u5973\u306e\u60e8\u3059\u304e\u308b\u77ac\u9593 \u9ebb\u85ac\u635c\u67fb\u5b98\u62f7\u554f \u5973\u635c\u67fb\u5b98 FILE 27 \u6ce2\u591a\u91ce\u7d50\u8863\u306e\u5834\u5408", "imgf": "https://www.goldenshark.xyz/images/DXMG-027.jpg", "href": "http://thz2.com/thread-283241-1-321.html", "dlnk": "http://thz2.com/forum.php?mod=attachment&aid=MjUxOTMxfDBiMmQzOTUxfDE1MjM5MjM0MDF8MHwyODMyNDE%3D"}, {"jref": "http://www.javlibrary.com/en/vl_searchbyid.php?keyword=ZRO-089", "_type": "dict", "code": "ZRO-089", "name": "\u521d\u7f8e\u6c99\u5e0c", "pdat": ["\r\n\u7247\u540d\uff1a\u901a\u5b66\u8def\u3067\u5f85\u3061\u4f0f\u305b\u3057\u3066\u8a98\u62d0\u3057\u305f\u5973\u5b50\u6821\u751f\u9054\u3092\u81ea\u5b85\u3067\u76e3\u7981\u3057\u6027\u5974\u96b7\u306b\u8abf\u6559\u3057\u305f\u8a18\u9332 4", "\r\n\u5bb9\u91cf\uff1a5.84Gb", "\r\n\u683c\u5f0f\uff1amkv", "\r\n\u914d\u4fe1\u958b\u59cb\u65e5\uff1a\u00a0 \u00a0 \u00a0 \u00a0 2015/01/14", "\r\n\u5546\u54c1\u767a\u58f2\u65e5\uff1a\u00a0 \u00a0 \u00a0 \u00a0 2015/01/10", "\r\n\u53ce\u9332\u6642\u9593\uff1a\u00a0 \u00a0 \u00a0 \u00a0 210\u5206 \uff08HD\u7248\uff1a210\u5206\uff09", "\r\n\u51fa\u6f14\u8005\uff1a\u00a0 \u00a0 \u00a0 \u00a0 ----", "\r\n\u76e3\u7763\uff1a\u00a0 \u00a0 \u00a0 \u00a0 ----", "\r\n\u30b7\u30ea\u30fc\u30ba\uff1a\u00a0 \u00a0 \u00a0 \u00a0 \u901a\u5b78\u8def\u3067\u5f85\u3061\u4f0f\u305b\u3057\u3066\u8a98\u62d0\u3057\u305f\u5973\u5b50\u6821\u751f\u9054\u3092\u81ea\u5b85\u3067\u76e3\u7981\u3057\u6027\u5974\u96b7\u306b\u8abf\u6559\u3057\u305f\u8a18\u9332", "\r\n\u30e1\u30fc\u30ab\u30fc\uff1a\u00a0 \u00a0 \u00a0 \u00a0 MAD", "\r\n\u30ec\u30fc\u30d9\u30eb\uff1a\u00a0 \u00a0 \u00a0 \u00a0 \u96f6", "\r\n\u30b8\u30e3\u30f3\u30eb\uff1a\u00a0 \u00a0 \u00a0 \u00a0 \u5b78\u751f\u670d\u00a0\u00a0\u8abf\u6559?\u5974\u96b7\u00a0\u00a0\u76e3\u7981\u00a0\u00a0\u5973\u5b50\u6821\u751f\u00a0\u00a0\u5f37\u59e6\u00a0\u00a0\u30cf\u30a4\u30d3\u30b8\u30e7\u30f3", "\r\n\u54c1\u756a\uff1a\u00a0 \u00a0 \u00a0 \u00a0 h_286zro00089", "\r\n\r\n"], "text": "[ZRO-089]\u901a\u5b66\u8def\u3067\u5f85\u3061\u4f0f\u305b\u3057\u3066\u8a98\u62d0\u3057\u305f\u5973\u5b50\u6821\u751f\u9054\u3092\u81ea\u5b85\u3067\u76e3\u7981\u3057\u6027\u5974\u96b7\u306b\u8abf\u6559\u3057\u305f\u8a18\u9332 4", "imgf": "https://www.goldenshark.xyz/images/ZRO-089.jpg", "href": "http://thz2.com/thread-283278-1-321.html", "dlnk": "http://thz2.com/forum.php?mod=attachment&aid=MjUxOTUwfDZlNWJjNTVifDE1MjM5MjM0MDF8MHwyODMyNzg%3D"}, {"jref": "http://www.javlibrary.com/en/vl_searchbyid.php?keyword=CEAD-027", "_type": "dict", "code": "CEAD-027", "name": "\u996d\u5188\u52a0\u5948\u5b50", "pdat": ["\r\n\u7247\u540d\uff1a\u9154\u3063\u3066\u5bdd\u305f\u65e6\u90a3\u306e\u6a2a\u3067\u7fa9\u7406\u306e\u5f1f\u3068 \u65e6\u90a3\u306b\u306f\u8a00\u3048\u306a\u3044\u4eba\u59bb\u306e\u5fc3\u306e\u5bc2\u3057\u3055\u3068\u9699\u9593\u3092\u57cb\u3081\u308b \u5bdd\u53d6\u3089\u308c\u8089\u6b32\u4ea4\u5c3e \u98ef\u5ca1\u304b\u306a\u3053", "\r\n\u5bb9\u91cf\uff1a1.77Gb", "\r\n\u683c\u5f0f\uff1amkv", "\r\n\u914d\u4fe1\u958b\u59cb\u65e5\uff1a\u00a0 \u00a0 \u00a0 \u00a0 2015/02/22", "\r\n\u5546\u54c1\u767a\u58f2\u65e5\uff1a\u00a0 \u00a0 \u00a0 \u00a0 2015/02/25", "\r\n\u53ce\u9332\u6642\u9593\uff1a\u00a0 \u00a0 \u00a0 \u00a0 127\u5206", "\r\n\u51fa\u6f14\u8005\uff1a\u00a0 \u00a0 \u00a0 \u00a0 \u98ef\u5ca1\u304b\u306a\u3053", "\r\n\u76e3\u7763\uff1a\u00a0 \u00a0 \u00a0 \u00a0 ----", "\r\n\u30b7\u30ea\u30fc\u30ba\uff1a\u00a0 \u00a0 \u00a0 \u00a0 ----", "\r\n\u30e1\u30fc\u30ab\u30fc\uff1a\u00a0 \u00a0 \u00a0 \u00a0 \u30bb\u30ec\u30d6\u306e\u53cb", "\r\n\u30ec\u30fc\u30d9\u30eb\uff1a\u00a0 \u00a0 \u00a0 \u00a0 \u30bb\u30ec\u30d6\u306e\u53cb", "\r\n\u30b8\u30e3\u30f3\u30eb\uff1a\u00a0 \u00a0 \u00a0 \u00a0 \u7368\u5360\u914d\u4fe1\u00a0\u00a0\u5358\u9ad4\u4f5c\u54c1\u00a0\u00a0\u9a0e\u4e57\u4f4d\u00a0\u00a0\u30d5\u30a7\u30e9\u00a0\u00a0\u30aa\u30ca\u30cb\u30fc\u00a0\u00a0\u4eba\u59bb\u00a0\u00a0\u719f\u5973", "\r\n\u54c1\u756a\uff1a\u00a0 \u00a0 \u00a0 \u00a0 cead00027", "\r\n\r\n"], "text": "[CEAD-027]\u9154\u3063\u3066\u5bdd\u305f\u65e6\u90a3\u306e\u6a2a\u3067\u7fa9\u7406\u306e\u5f1f\u3068", "imgf": "https://www.goldenshark.xyz/images/CEAD-027.jpg", "href": "http://thz2.com/thread-283187-1-321.html", "dlnk": "http://thz2.com/forum.php?mod=attachment&aid=MjUxODk2fGIxOTM2MzYyfDE1MjM5MjM0MDJ8MHwyODMxODc%3D"}, {"jref": "http://www.javlibrary.com/en/vl_searchbyid.php?keyword=CETD-240", "_type": "dict", "code": "CETD-240", "name": "\u6ce2\u591a\u91ce\u7ed3\u8863", "pdat": ["\r\n\u7247\u540d\uff1a\u30ef\u30ad\u6bdb\u3067\u8a98\u60d1\u3059\u308b\u75f4\u5973\u793e\u9577 \u8272\u8276\u5302\u3044\u6700\u9ad8\u306e\u30ef\u30ad\u6bdb\u6311\u767a\u75f4\u5973\u30cf\u30e1\u5feb\u611f\u64e6\u308a\u3064\u3051\u30bb\u30c3\u30af\u30b9\u7121\u5dee\u5225\u30c1\u25cb\u30dd\u72e9\u308a\u306e\u7d50\u672b \u6ce2\u591a\u91ce\u7d50\u8863", "\r\n\u5bb9\u91cf\uff1a1.86GB", "\r\n\u683c\u5f0f\uff1amkv", "\r\n\u914d\u4fe1\u958b\u59cb\u65e5\uff1a\u00a0 \u00a0 \u00a0 \u00a0 2015/02/22", "\r\n\u5546\u54c1\u767a\u58f2\u65e5\uff1a\u00a0 \u00a0 \u00a0 \u00a0 2015/02/25", "\r\n\u53ce\u9332\u6642\u9593\uff1a\u00a0 \u00a0 \u00a0 \u00a0 133\u5206", "\r\n\u51fa\u6f14\u8005\uff1a\u00a0 \u00a0 \u00a0 \u00a0 \u6ce2\u591a\u91ce\u7d50\u8863", "\r\n\u76e3\u7763\uff1a\u00a0 \u00a0 \u00a0 \u00a0 \u9ed2\u9f8d\u6b66", "\r\n\u30b7\u30ea\u30fc\u30ba\uff1a\u00a0 \u00a0 \u00a0 \u00a0 \u30ef\u30ad\u6bdb\u3067\u8a98\u60d1\u3059\u308b", "\r\n\u30e1\u30fc\u30ab\u30fc\uff1a\u00a0 \u00a0 \u00a0 \u00a0 \u30bb\u30ec\u30d6\u306e\u53cb", "\r\n\u30ec\u30fc\u30d9\u30eb\uff1a\u00a0 \u00a0 \u00a0 \u00a0 \u30bb\u30ec\u30d6\u306e\u53cb", "\r\n\u30b8\u30e3\u30f3\u30eb\uff1a\u00a0 \u00a0 \u00a0 \u00a0 \u7368\u5360\u914d\u4fe1\u00a0\u00a0\u5358\u9ad4\u4f5c\u54c1\u00a0\u00a0\u9a0e\u4e57\u4f4d\u00a0\u00a0\u30aa\u30ca\u30cb\u30fc\u00a0\u00a0\u7661\u5973\u00a0\u00a0\u719f\u5973", "\r\n\u54c1\u756a\uff1a\u00a0 \u00a0 \u00a0 \u00a0 cetd00240", "\r\n\r\n"], "text": "[CETD-240]\u30ef\u30ad\u6bdb\u3067\u8a98\u60d1\u3059\u308b\u75f4\u5973\u793e\u9577 \u6ce2\u591a\u91ce\u7d50\u8863", "imgf": "https://www.goldenshark.xyz/images/CETD-240.jpg", "href": "http://thz2.com/thread-283209-1-321.html", "dlnk": "http://thz2.com/forum.php?mod=attachment&aid=MjUxOTA2fDZkNGViZWVkfDE1MjM5MjM0MDJ8MHwyODMyMDk%3D"}]